package com.google.android.gms.ads.internal.client;

import android.os.Binder;
import android.os.IBinder;
import android.os.IInterface;
import android.os.Parcel;
import com.google.android.gms.ads.internal.reward.client.d;
import com.google.android.gms.ads.internal.reward.client.d.a;
import com.google.android.gms.c.e;
import com.google.android.gms.c.e.a;
import com.google.android.gms.internal.ur;
import com.google.android.gms.internal.ur.a;
import com.google.android.gms.internal.yy;
import com.google.android.gms.internal.yy.a;
import com.google.android.gms.internal.zd;
import com.google.android.gms.internal.zd.a;

public abstract interface ak
  extends IInterface
{
  public abstract e a();
  
  public abstract void a(AdSizeParcel paramAdSizeParcel);
  
  public abstract void a(VideoOptionsParcel paramVideoOptionsParcel);
  
  public abstract void a(af paramaf);
  
  public abstract void a(ag paramag);
  
  public abstract void a(am paramam);
  
  public abstract void a(ao paramao);
  
  public abstract void a(d paramd);
  
  public abstract void a(ur paramur);
  
  public abstract void a(yy paramyy);
  
  public abstract void a(zd paramzd, String paramString);
  
  public abstract void a(String paramString);
  
  public abstract void a(boolean paramBoolean);
  
  public abstract boolean a(AdRequestParcel paramAdRequestParcel);
  
  public abstract void b();
  
  public abstract boolean c();
  
  public abstract void c_();
  
  public abstract void d();
  
  public abstract void f();
  
  public abstract void g_();
  
  public abstract void h();
  
  public abstract AdSizeParcel i();
  
  public abstract String j();
  
  public abstract boolean k();
  
  public abstract c l();
  
  public static abstract class a
    extends Binder
    implements ak
  {
    public a()
    {
      attachInterface(this, "com.google.android.gms.ads.internal.client.IAdManager");
    }
    
    public static ak a(IBinder paramIBinder)
    {
      if (paramIBinder == null) {
        return null;
      }
      IInterface localIInterface = paramIBinder.queryLocalInterface("com.google.android.gms.ads.internal.client.IAdManager");
      if ((localIInterface != null) && ((localIInterface instanceof ak))) {
        return (ak)localIInterface;
      }
      return new a(paramIBinder);
    }
    
    public IBinder asBinder()
    {
      return this;
    }
    
    public boolean onTransact(int paramInt1, Parcel paramParcel1, Parcel paramParcel2, int paramInt2)
    {
      Object localObject2 = null;
      Object localObject3 = null;
      e locale = null;
      Object localObject4 = null;
      Object localObject1 = null;
      boolean bool = false;
      int j = 0;
      int i = 0;
      switch (paramInt1)
      {
      default: 
        return super.onTransact(paramInt1, paramParcel1, paramParcel2, paramInt2);
      case 1598968902: 
        paramParcel2.writeString("com.google.android.gms.ads.internal.client.IAdManager");
        return true;
      case 1: 
        paramParcel1.enforceInterface("com.google.android.gms.ads.internal.client.IAdManager");
        locale = a();
        paramParcel2.writeNoException();
        paramParcel1 = (Parcel)localObject1;
        if (locale != null) {
          paramParcel1 = locale.asBinder();
        }
        paramParcel2.writeStrongBinder(paramParcel1);
        return true;
      case 2: 
        paramParcel1.enforceInterface("com.google.android.gms.ads.internal.client.IAdManager");
        b();
        paramParcel2.writeNoException();
        return true;
      case 3: 
        paramParcel1.enforceInterface("com.google.android.gms.ads.internal.client.IAdManager");
        bool = c();
        paramParcel2.writeNoException();
        if (bool) {}
        for (paramInt1 = 1;; paramInt1 = 0)
        {
          paramParcel2.writeInt(paramInt1);
          return true;
        }
      case 4: 
        paramParcel1.enforceInterface("com.google.android.gms.ads.internal.client.IAdManager");
        localObject1 = localObject2;
        if (paramParcel1.readInt() != 0) {
          localObject1 = (AdRequestParcel)AdRequestParcel.CREATOR.createFromParcel(paramParcel1);
        }
        bool = a((AdRequestParcel)localObject1);
        paramParcel2.writeNoException();
        paramInt1 = i;
        if (bool) {
          paramInt1 = 1;
        }
        paramParcel2.writeInt(paramInt1);
        return true;
      case 5: 
        paramParcel1.enforceInterface("com.google.android.gms.ads.internal.client.IAdManager");
        d();
        paramParcel2.writeNoException();
        return true;
      case 6: 
        paramParcel1.enforceInterface("com.google.android.gms.ads.internal.client.IAdManager");
        c_();
        paramParcel2.writeNoException();
        return true;
      case 7: 
        paramParcel1.enforceInterface("com.google.android.gms.ads.internal.client.IAdManager");
        a(ag.a.a(paramParcel1.readStrongBinder()));
        paramParcel2.writeNoException();
        return true;
      case 8: 
        paramParcel1.enforceInterface("com.google.android.gms.ads.internal.client.IAdManager");
        a(am.a.a(paramParcel1.readStrongBinder()));
        paramParcel2.writeNoException();
        return true;
      case 9: 
        paramParcel1.enforceInterface("com.google.android.gms.ads.internal.client.IAdManager");
        f();
        paramParcel2.writeNoException();
        return true;
      case 10: 
        paramParcel1.enforceInterface("com.google.android.gms.ads.internal.client.IAdManager");
        g_();
        paramParcel2.writeNoException();
        return true;
      case 11: 
        paramParcel1.enforceInterface("com.google.android.gms.ads.internal.client.IAdManager");
        h();
        paramParcel2.writeNoException();
        return true;
      case 12: 
        paramParcel1.enforceInterface("com.google.android.gms.ads.internal.client.IAdManager");
        paramParcel1 = i();
        paramParcel2.writeNoException();
        if (paramParcel1 != null)
        {
          paramParcel2.writeInt(1);
          paramParcel1.writeToParcel(paramParcel2, 1);
          return true;
        }
        paramParcel2.writeInt(0);
        return true;
      case 13: 
        paramParcel1.enforceInterface("com.google.android.gms.ads.internal.client.IAdManager");
        localObject1 = localObject3;
        if (paramParcel1.readInt() != 0) {
          localObject1 = (AdSizeParcel)AdSizeParcel.CREATOR.createFromParcel(paramParcel1);
        }
        a((AdSizeParcel)localObject1);
        paramParcel2.writeNoException();
        return true;
      case 14: 
        paramParcel1.enforceInterface("com.google.android.gms.ads.internal.client.IAdManager");
        a(yy.a.a(paramParcel1.readStrongBinder()));
        paramParcel2.writeNoException();
        return true;
      case 15: 
        paramParcel1.enforceInterface("com.google.android.gms.ads.internal.client.IAdManager");
        a(zd.a.a(paramParcel1.readStrongBinder()), paramParcel1.readString());
        paramParcel2.writeNoException();
        return true;
      case 18: 
        paramParcel1.enforceInterface("com.google.android.gms.ads.internal.client.IAdManager");
        paramParcel1 = j();
        paramParcel2.writeNoException();
        paramParcel2.writeString(paramParcel1);
        return true;
      case 19: 
        paramParcel1.enforceInterface("com.google.android.gms.ads.internal.client.IAdManager");
        a(ur.a.a(paramParcel1.readStrongBinder()));
        paramParcel2.writeNoException();
        return true;
      case 20: 
        paramParcel1.enforceInterface("com.google.android.gms.ads.internal.client.IAdManager");
        a(af.a.a(paramParcel1.readStrongBinder()));
        paramParcel2.writeNoException();
        return true;
      case 21: 
        paramParcel1.enforceInterface("com.google.android.gms.ads.internal.client.IAdManager");
        a(ao.a.a(paramParcel1.readStrongBinder()));
        paramParcel2.writeNoException();
        return true;
      case 22: 
        paramParcel1.enforceInterface("com.google.android.gms.ads.internal.client.IAdManager");
        if (paramParcel1.readInt() != 0) {
          bool = true;
        }
        a(bool);
        paramParcel2.writeNoException();
        return true;
      case 23: 
        paramParcel1.enforceInterface("com.google.android.gms.ads.internal.client.IAdManager");
        bool = k();
        paramParcel2.writeNoException();
        paramInt1 = j;
        if (bool) {
          paramInt1 = 1;
        }
        paramParcel2.writeInt(paramInt1);
        return true;
      case 24: 
        paramParcel1.enforceInterface("com.google.android.gms.ads.internal.client.IAdManager");
        a(d.a.a(paramParcel1.readStrongBinder()));
        paramParcel2.writeNoException();
        return true;
      case 25: 
        paramParcel1.enforceInterface("com.google.android.gms.ads.internal.client.IAdManager");
        a(paramParcel1.readString());
        paramParcel2.writeNoException();
        return true;
      case 26: 
        paramParcel1.enforceInterface("com.google.android.gms.ads.internal.client.IAdManager");
        localObject1 = l();
        paramParcel2.writeNoException();
        paramParcel1 = locale;
        if (localObject1 != null) {
          paramParcel1 = ((c)localObject1).asBinder();
        }
        paramParcel2.writeStrongBinder(paramParcel1);
        return true;
      }
      paramParcel1.enforceInterface("com.google.android.gms.ads.internal.client.IAdManager");
      localObject1 = localObject4;
      if (paramParcel1.readInt() != 0) {
        localObject1 = (VideoOptionsParcel)VideoOptionsParcel.CREATOR.createFromParcel(paramParcel1);
      }
      a((VideoOptionsParcel)localObject1);
      paramParcel2.writeNoException();
      return true;
    }
    
    private static class a
      implements ak
    {
      private IBinder a;
      
      a(IBinder paramIBinder)
      {
        this.a = paramIBinder;
      }
      
      public e a()
      {
        Parcel localParcel1 = Parcel.obtain();
        Parcel localParcel2 = Parcel.obtain();
        try
        {
          localParcel1.writeInterfaceToken("com.google.android.gms.ads.internal.client.IAdManager");
          this.a.transact(1, localParcel1, localParcel2, 0);
          localParcel2.readException();
          e locale = e.a.a(localParcel2.readStrongBinder());
          return locale;
        }
        finally
        {
          localParcel2.recycle();
          localParcel1.recycle();
        }
      }
      
      /* Error */
      public void a(AdSizeParcel paramAdSizeParcel)
      {
        // Byte code:
        //   0: invokestatic 25	android/os/Parcel:obtain	()Landroid/os/Parcel;
        //   3: astore_2
        //   4: invokestatic 25	android/os/Parcel:obtain	()Landroid/os/Parcel;
        //   7: astore_3
        //   8: aload_2
        //   9: ldc 27
        //   11: invokevirtual 31	android/os/Parcel:writeInterfaceToken	(Ljava/lang/String;)V
        //   14: aload_1
        //   15: ifnull +42 -> 57
        //   18: aload_2
        //   19: iconst_1
        //   20: invokevirtual 57	android/os/Parcel:writeInt	(I)V
        //   23: aload_1
        //   24: aload_2
        //   25: iconst_0
        //   26: invokevirtual 63	com/google/android/gms/ads/internal/client/AdSizeParcel:writeToParcel	(Landroid/os/Parcel;I)V
        //   29: aload_0
        //   30: getfield 17	com/google/android/gms/ads/internal/client/ak$a$a:a	Landroid/os/IBinder;
        //   33: bipush 13
        //   35: aload_2
        //   36: aload_3
        //   37: iconst_0
        //   38: invokeinterface 37 5 0
        //   43: pop
        //   44: aload_3
        //   45: invokevirtual 40	android/os/Parcel:readException	()V
        //   48: aload_3
        //   49: invokevirtual 52	android/os/Parcel:recycle	()V
        //   52: aload_2
        //   53: invokevirtual 52	android/os/Parcel:recycle	()V
        //   56: return
        //   57: aload_2
        //   58: iconst_0
        //   59: invokevirtual 57	android/os/Parcel:writeInt	(I)V
        //   62: goto -33 -> 29
        //   65: astore_1
        //   66: aload_3
        //   67: invokevirtual 52	android/os/Parcel:recycle	()V
        //   70: aload_2
        //   71: invokevirtual 52	android/os/Parcel:recycle	()V
        //   74: aload_1
        //   75: athrow
        // Local variable table:
        //   start	length	slot	name	signature
        //   0	76	0	this	a
        //   0	76	1	paramAdSizeParcel	AdSizeParcel
        //   3	68	2	localParcel1	Parcel
        //   7	60	3	localParcel2	Parcel
        // Exception table:
        //   from	to	target	type
        //   8	14	65	finally
        //   18	29	65	finally
        //   29	48	65	finally
        //   57	62	65	finally
      }
      
      /* Error */
      public void a(VideoOptionsParcel paramVideoOptionsParcel)
      {
        // Byte code:
        //   0: invokestatic 25	android/os/Parcel:obtain	()Landroid/os/Parcel;
        //   3: astore_2
        //   4: invokestatic 25	android/os/Parcel:obtain	()Landroid/os/Parcel;
        //   7: astore_3
        //   8: aload_2
        //   9: ldc 27
        //   11: invokevirtual 31	android/os/Parcel:writeInterfaceToken	(Ljava/lang/String;)V
        //   14: aload_1
        //   15: ifnull +42 -> 57
        //   18: aload_2
        //   19: iconst_1
        //   20: invokevirtual 57	android/os/Parcel:writeInt	(I)V
        //   23: aload_1
        //   24: aload_2
        //   25: iconst_0
        //   26: invokevirtual 67	com/google/android/gms/ads/internal/client/VideoOptionsParcel:writeToParcel	(Landroid/os/Parcel;I)V
        //   29: aload_0
        //   30: getfield 17	com/google/android/gms/ads/internal/client/ak$a$a:a	Landroid/os/IBinder;
        //   33: bipush 29
        //   35: aload_2
        //   36: aload_3
        //   37: iconst_0
        //   38: invokeinterface 37 5 0
        //   43: pop
        //   44: aload_3
        //   45: invokevirtual 40	android/os/Parcel:readException	()V
        //   48: aload_3
        //   49: invokevirtual 52	android/os/Parcel:recycle	()V
        //   52: aload_2
        //   53: invokevirtual 52	android/os/Parcel:recycle	()V
        //   56: return
        //   57: aload_2
        //   58: iconst_0
        //   59: invokevirtual 57	android/os/Parcel:writeInt	(I)V
        //   62: goto -33 -> 29
        //   65: astore_1
        //   66: aload_3
        //   67: invokevirtual 52	android/os/Parcel:recycle	()V
        //   70: aload_2
        //   71: invokevirtual 52	android/os/Parcel:recycle	()V
        //   74: aload_1
        //   75: athrow
        // Local variable table:
        //   start	length	slot	name	signature
        //   0	76	0	this	a
        //   0	76	1	paramVideoOptionsParcel	VideoOptionsParcel
        //   3	68	2	localParcel1	Parcel
        //   7	60	3	localParcel2	Parcel
        // Exception table:
        //   from	to	target	type
        //   8	14	65	finally
        //   18	29	65	finally
        //   29	48	65	finally
        //   57	62	65	finally
      }
      
      /* Error */
      public void a(af paramaf)
      {
        // Byte code:
        //   0: invokestatic 25	android/os/Parcel:obtain	()Landroid/os/Parcel;
        //   3: astore_2
        //   4: invokestatic 25	android/os/Parcel:obtain	()Landroid/os/Parcel;
        //   7: astore_3
        //   8: aload_2
        //   9: ldc 27
        //   11: invokevirtual 31	android/os/Parcel:writeInterfaceToken	(Ljava/lang/String;)V
        //   14: aload_1
        //   15: ifnull +43 -> 58
        //   18: aload_1
        //   19: invokeinterface 73 1 0
        //   24: astore_1
        //   25: aload_2
        //   26: aload_1
        //   27: invokevirtual 76	android/os/Parcel:writeStrongBinder	(Landroid/os/IBinder;)V
        //   30: aload_0
        //   31: getfield 17	com/google/android/gms/ads/internal/client/ak$a$a:a	Landroid/os/IBinder;
        //   34: bipush 20
        //   36: aload_2
        //   37: aload_3
        //   38: iconst_0
        //   39: invokeinterface 37 5 0
        //   44: pop
        //   45: aload_3
        //   46: invokevirtual 40	android/os/Parcel:readException	()V
        //   49: aload_3
        //   50: invokevirtual 52	android/os/Parcel:recycle	()V
        //   53: aload_2
        //   54: invokevirtual 52	android/os/Parcel:recycle	()V
        //   57: return
        //   58: aconst_null
        //   59: astore_1
        //   60: goto -35 -> 25
        //   63: astore_1
        //   64: aload_3
        //   65: invokevirtual 52	android/os/Parcel:recycle	()V
        //   68: aload_2
        //   69: invokevirtual 52	android/os/Parcel:recycle	()V
        //   72: aload_1
        //   73: athrow
        // Local variable table:
        //   start	length	slot	name	signature
        //   0	74	0	this	a
        //   0	74	1	paramaf	af
        //   3	66	2	localParcel1	Parcel
        //   7	58	3	localParcel2	Parcel
        // Exception table:
        //   from	to	target	type
        //   8	14	63	finally
        //   18	25	63	finally
        //   25	49	63	finally
      }
      
      /* Error */
      public void a(ag paramag)
      {
        // Byte code:
        //   0: invokestatic 25	android/os/Parcel:obtain	()Landroid/os/Parcel;
        //   3: astore_2
        //   4: invokestatic 25	android/os/Parcel:obtain	()Landroid/os/Parcel;
        //   7: astore_3
        //   8: aload_2
        //   9: ldc 27
        //   11: invokevirtual 31	android/os/Parcel:writeInterfaceToken	(Ljava/lang/String;)V
        //   14: aload_1
        //   15: ifnull +43 -> 58
        //   18: aload_1
        //   19: invokeinterface 80 1 0
        //   24: astore_1
        //   25: aload_2
        //   26: aload_1
        //   27: invokevirtual 76	android/os/Parcel:writeStrongBinder	(Landroid/os/IBinder;)V
        //   30: aload_0
        //   31: getfield 17	com/google/android/gms/ads/internal/client/ak$a$a:a	Landroid/os/IBinder;
        //   34: bipush 7
        //   36: aload_2
        //   37: aload_3
        //   38: iconst_0
        //   39: invokeinterface 37 5 0
        //   44: pop
        //   45: aload_3
        //   46: invokevirtual 40	android/os/Parcel:readException	()V
        //   49: aload_3
        //   50: invokevirtual 52	android/os/Parcel:recycle	()V
        //   53: aload_2
        //   54: invokevirtual 52	android/os/Parcel:recycle	()V
        //   57: return
        //   58: aconst_null
        //   59: astore_1
        //   60: goto -35 -> 25
        //   63: astore_1
        //   64: aload_3
        //   65: invokevirtual 52	android/os/Parcel:recycle	()V
        //   68: aload_2
        //   69: invokevirtual 52	android/os/Parcel:recycle	()V
        //   72: aload_1
        //   73: athrow
        // Local variable table:
        //   start	length	slot	name	signature
        //   0	74	0	this	a
        //   0	74	1	paramag	ag
        //   3	66	2	localParcel1	Parcel
        //   7	58	3	localParcel2	Parcel
        // Exception table:
        //   from	to	target	type
        //   8	14	63	finally
        //   18	25	63	finally
        //   25	49	63	finally
      }
      
      /* Error */
      public void a(am paramam)
      {
        // Byte code:
        //   0: invokestatic 25	android/os/Parcel:obtain	()Landroid/os/Parcel;
        //   3: astore_2
        //   4: invokestatic 25	android/os/Parcel:obtain	()Landroid/os/Parcel;
        //   7: astore_3
        //   8: aload_2
        //   9: ldc 27
        //   11: invokevirtual 31	android/os/Parcel:writeInterfaceToken	(Ljava/lang/String;)V
        //   14: aload_1
        //   15: ifnull +43 -> 58
        //   18: aload_1
        //   19: invokeinterface 84 1 0
        //   24: astore_1
        //   25: aload_2
        //   26: aload_1
        //   27: invokevirtual 76	android/os/Parcel:writeStrongBinder	(Landroid/os/IBinder;)V
        //   30: aload_0
        //   31: getfield 17	com/google/android/gms/ads/internal/client/ak$a$a:a	Landroid/os/IBinder;
        //   34: bipush 8
        //   36: aload_2
        //   37: aload_3
        //   38: iconst_0
        //   39: invokeinterface 37 5 0
        //   44: pop
        //   45: aload_3
        //   46: invokevirtual 40	android/os/Parcel:readException	()V
        //   49: aload_3
        //   50: invokevirtual 52	android/os/Parcel:recycle	()V
        //   53: aload_2
        //   54: invokevirtual 52	android/os/Parcel:recycle	()V
        //   57: return
        //   58: aconst_null
        //   59: astore_1
        //   60: goto -35 -> 25
        //   63: astore_1
        //   64: aload_3
        //   65: invokevirtual 52	android/os/Parcel:recycle	()V
        //   68: aload_2
        //   69: invokevirtual 52	android/os/Parcel:recycle	()V
        //   72: aload_1
        //   73: athrow
        // Local variable table:
        //   start	length	slot	name	signature
        //   0	74	0	this	a
        //   0	74	1	paramam	am
        //   3	66	2	localParcel1	Parcel
        //   7	58	3	localParcel2	Parcel
        // Exception table:
        //   from	to	target	type
        //   8	14	63	finally
        //   18	25	63	finally
        //   25	49	63	finally
      }
      
      /* Error */
      public void a(ao paramao)
      {
        // Byte code:
        //   0: invokestatic 25	android/os/Parcel:obtain	()Landroid/os/Parcel;
        //   3: astore_2
        //   4: invokestatic 25	android/os/Parcel:obtain	()Landroid/os/Parcel;
        //   7: astore_3
        //   8: aload_2
        //   9: ldc 27
        //   11: invokevirtual 31	android/os/Parcel:writeInterfaceToken	(Ljava/lang/String;)V
        //   14: aload_1
        //   15: ifnull +43 -> 58
        //   18: aload_1
        //   19: invokeinterface 88 1 0
        //   24: astore_1
        //   25: aload_2
        //   26: aload_1
        //   27: invokevirtual 76	android/os/Parcel:writeStrongBinder	(Landroid/os/IBinder;)V
        //   30: aload_0
        //   31: getfield 17	com/google/android/gms/ads/internal/client/ak$a$a:a	Landroid/os/IBinder;
        //   34: bipush 21
        //   36: aload_2
        //   37: aload_3
        //   38: iconst_0
        //   39: invokeinterface 37 5 0
        //   44: pop
        //   45: aload_3
        //   46: invokevirtual 40	android/os/Parcel:readException	()V
        //   49: aload_3
        //   50: invokevirtual 52	android/os/Parcel:recycle	()V
        //   53: aload_2
        //   54: invokevirtual 52	android/os/Parcel:recycle	()V
        //   57: return
        //   58: aconst_null
        //   59: astore_1
        //   60: goto -35 -> 25
        //   63: astore_1
        //   64: aload_3
        //   65: invokevirtual 52	android/os/Parcel:recycle	()V
        //   68: aload_2
        //   69: invokevirtual 52	android/os/Parcel:recycle	()V
        //   72: aload_1
        //   73: athrow
        // Local variable table:
        //   start	length	slot	name	signature
        //   0	74	0	this	a
        //   0	74	1	paramao	ao
        //   3	66	2	localParcel1	Parcel
        //   7	58	3	localParcel2	Parcel
        // Exception table:
        //   from	to	target	type
        //   8	14	63	finally
        //   18	25	63	finally
        //   25	49	63	finally
      }
      
      /* Error */
      public void a(d paramd)
      {
        // Byte code:
        //   0: invokestatic 25	android/os/Parcel:obtain	()Landroid/os/Parcel;
        //   3: astore_2
        //   4: invokestatic 25	android/os/Parcel:obtain	()Landroid/os/Parcel;
        //   7: astore_3
        //   8: aload_2
        //   9: ldc 27
        //   11: invokevirtual 31	android/os/Parcel:writeInterfaceToken	(Ljava/lang/String;)V
        //   14: aload_1
        //   15: ifnull +43 -> 58
        //   18: aload_1
        //   19: invokeinterface 92 1 0
        //   24: astore_1
        //   25: aload_2
        //   26: aload_1
        //   27: invokevirtual 76	android/os/Parcel:writeStrongBinder	(Landroid/os/IBinder;)V
        //   30: aload_0
        //   31: getfield 17	com/google/android/gms/ads/internal/client/ak$a$a:a	Landroid/os/IBinder;
        //   34: bipush 24
        //   36: aload_2
        //   37: aload_3
        //   38: iconst_0
        //   39: invokeinterface 37 5 0
        //   44: pop
        //   45: aload_3
        //   46: invokevirtual 40	android/os/Parcel:readException	()V
        //   49: aload_3
        //   50: invokevirtual 52	android/os/Parcel:recycle	()V
        //   53: aload_2
        //   54: invokevirtual 52	android/os/Parcel:recycle	()V
        //   57: return
        //   58: aconst_null
        //   59: astore_1
        //   60: goto -35 -> 25
        //   63: astore_1
        //   64: aload_3
        //   65: invokevirtual 52	android/os/Parcel:recycle	()V
        //   68: aload_2
        //   69: invokevirtual 52	android/os/Parcel:recycle	()V
        //   72: aload_1
        //   73: athrow
        // Local variable table:
        //   start	length	slot	name	signature
        //   0	74	0	this	a
        //   0	74	1	paramd	d
        //   3	66	2	localParcel1	Parcel
        //   7	58	3	localParcel2	Parcel
        // Exception table:
        //   from	to	target	type
        //   8	14	63	finally
        //   18	25	63	finally
        //   25	49	63	finally
      }
      
      /* Error */
      public void a(ur paramur)
      {
        // Byte code:
        //   0: invokestatic 25	android/os/Parcel:obtain	()Landroid/os/Parcel;
        //   3: astore_2
        //   4: invokestatic 25	android/os/Parcel:obtain	()Landroid/os/Parcel;
        //   7: astore_3
        //   8: aload_2
        //   9: ldc 27
        //   11: invokevirtual 31	android/os/Parcel:writeInterfaceToken	(Ljava/lang/String;)V
        //   14: aload_1
        //   15: ifnull +43 -> 58
        //   18: aload_1
        //   19: invokeinterface 96 1 0
        //   24: astore_1
        //   25: aload_2
        //   26: aload_1
        //   27: invokevirtual 76	android/os/Parcel:writeStrongBinder	(Landroid/os/IBinder;)V
        //   30: aload_0
        //   31: getfield 17	com/google/android/gms/ads/internal/client/ak$a$a:a	Landroid/os/IBinder;
        //   34: bipush 19
        //   36: aload_2
        //   37: aload_3
        //   38: iconst_0
        //   39: invokeinterface 37 5 0
        //   44: pop
        //   45: aload_3
        //   46: invokevirtual 40	android/os/Parcel:readException	()V
        //   49: aload_3
        //   50: invokevirtual 52	android/os/Parcel:recycle	()V
        //   53: aload_2
        //   54: invokevirtual 52	android/os/Parcel:recycle	()V
        //   57: return
        //   58: aconst_null
        //   59: astore_1
        //   60: goto -35 -> 25
        //   63: astore_1
        //   64: aload_3
        //   65: invokevirtual 52	android/os/Parcel:recycle	()V
        //   68: aload_2
        //   69: invokevirtual 52	android/os/Parcel:recycle	()V
        //   72: aload_1
        //   73: athrow
        // Local variable table:
        //   start	length	slot	name	signature
        //   0	74	0	this	a
        //   0	74	1	paramur	ur
        //   3	66	2	localParcel1	Parcel
        //   7	58	3	localParcel2	Parcel
        // Exception table:
        //   from	to	target	type
        //   8	14	63	finally
        //   18	25	63	finally
        //   25	49	63	finally
      }
      
      /* Error */
      public void a(yy paramyy)
      {
        // Byte code:
        //   0: invokestatic 25	android/os/Parcel:obtain	()Landroid/os/Parcel;
        //   3: astore_2
        //   4: invokestatic 25	android/os/Parcel:obtain	()Landroid/os/Parcel;
        //   7: astore_3
        //   8: aload_2
        //   9: ldc 27
        //   11: invokevirtual 31	android/os/Parcel:writeInterfaceToken	(Ljava/lang/String;)V
        //   14: aload_1
        //   15: ifnull +43 -> 58
        //   18: aload_1
        //   19: invokeinterface 100 1 0
        //   24: astore_1
        //   25: aload_2
        //   26: aload_1
        //   27: invokevirtual 76	android/os/Parcel:writeStrongBinder	(Landroid/os/IBinder;)V
        //   30: aload_0
        //   31: getfield 17	com/google/android/gms/ads/internal/client/ak$a$a:a	Landroid/os/IBinder;
        //   34: bipush 14
        //   36: aload_2
        //   37: aload_3
        //   38: iconst_0
        //   39: invokeinterface 37 5 0
        //   44: pop
        //   45: aload_3
        //   46: invokevirtual 40	android/os/Parcel:readException	()V
        //   49: aload_3
        //   50: invokevirtual 52	android/os/Parcel:recycle	()V
        //   53: aload_2
        //   54: invokevirtual 52	android/os/Parcel:recycle	()V
        //   57: return
        //   58: aconst_null
        //   59: astore_1
        //   60: goto -35 -> 25
        //   63: astore_1
        //   64: aload_3
        //   65: invokevirtual 52	android/os/Parcel:recycle	()V
        //   68: aload_2
        //   69: invokevirtual 52	android/os/Parcel:recycle	()V
        //   72: aload_1
        //   73: athrow
        // Local variable table:
        //   start	length	slot	name	signature
        //   0	74	0	this	a
        //   0	74	1	paramyy	yy
        //   3	66	2	localParcel1	Parcel
        //   7	58	3	localParcel2	Parcel
        // Exception table:
        //   from	to	target	type
        //   8	14	63	finally
        //   18	25	63	finally
        //   25	49	63	finally
      }
      
      /* Error */
      public void a(zd paramzd, String paramString)
      {
        // Byte code:
        //   0: invokestatic 25	android/os/Parcel:obtain	()Landroid/os/Parcel;
        //   3: astore_3
        //   4: invokestatic 25	android/os/Parcel:obtain	()Landroid/os/Parcel;
        //   7: astore 4
        //   9: aload_3
        //   10: ldc 27
        //   12: invokevirtual 31	android/os/Parcel:writeInterfaceToken	(Ljava/lang/String;)V
        //   15: aload_1
        //   16: ifnull +51 -> 67
        //   19: aload_1
        //   20: invokeinterface 104 1 0
        //   25: astore_1
        //   26: aload_3
        //   27: aload_1
        //   28: invokevirtual 76	android/os/Parcel:writeStrongBinder	(Landroid/os/IBinder;)V
        //   31: aload_3
        //   32: aload_2
        //   33: invokevirtual 107	android/os/Parcel:writeString	(Ljava/lang/String;)V
        //   36: aload_0
        //   37: getfield 17	com/google/android/gms/ads/internal/client/ak$a$a:a	Landroid/os/IBinder;
        //   40: bipush 15
        //   42: aload_3
        //   43: aload 4
        //   45: iconst_0
        //   46: invokeinterface 37 5 0
        //   51: pop
        //   52: aload 4
        //   54: invokevirtual 40	android/os/Parcel:readException	()V
        //   57: aload 4
        //   59: invokevirtual 52	android/os/Parcel:recycle	()V
        //   62: aload_3
        //   63: invokevirtual 52	android/os/Parcel:recycle	()V
        //   66: return
        //   67: aconst_null
        //   68: astore_1
        //   69: goto -43 -> 26
        //   72: astore_1
        //   73: aload 4
        //   75: invokevirtual 52	android/os/Parcel:recycle	()V
        //   78: aload_3
        //   79: invokevirtual 52	android/os/Parcel:recycle	()V
        //   82: aload_1
        //   83: athrow
        // Local variable table:
        //   start	length	slot	name	signature
        //   0	84	0	this	a
        //   0	84	1	paramzd	zd
        //   0	84	2	paramString	String
        //   3	76	3	localParcel1	Parcel
        //   7	67	4	localParcel2	Parcel
        // Exception table:
        //   from	to	target	type
        //   9	15	72	finally
        //   19	26	72	finally
        //   26	57	72	finally
      }
      
      public void a(String paramString)
      {
        Parcel localParcel1 = Parcel.obtain();
        Parcel localParcel2 = Parcel.obtain();
        try
        {
          localParcel1.writeInterfaceToken("com.google.android.gms.ads.internal.client.IAdManager");
          localParcel1.writeString(paramString);
          this.a.transact(25, localParcel1, localParcel2, 0);
          localParcel2.readException();
          return;
        }
        finally
        {
          localParcel2.recycle();
          localParcel1.recycle();
        }
      }
      
      public void a(boolean paramBoolean)
      {
        int i = 0;
        Parcel localParcel1 = Parcel.obtain();
        Parcel localParcel2 = Parcel.obtain();
        try
        {
          localParcel1.writeInterfaceToken("com.google.android.gms.ads.internal.client.IAdManager");
          if (paramBoolean) {
            i = 1;
          }
          localParcel1.writeInt(i);
          this.a.transact(22, localParcel1, localParcel2, 0);
          localParcel2.readException();
          return;
        }
        finally
        {
          localParcel2.recycle();
          localParcel1.recycle();
        }
      }
      
      public boolean a(AdRequestParcel paramAdRequestParcel)
      {
        boolean bool = true;
        Parcel localParcel1 = Parcel.obtain();
        Parcel localParcel2 = Parcel.obtain();
        for (;;)
        {
          try
          {
            localParcel1.writeInterfaceToken("com.google.android.gms.ads.internal.client.IAdManager");
            if (paramAdRequestParcel != null)
            {
              localParcel1.writeInt(1);
              paramAdRequestParcel.writeToParcel(localParcel1, 0);
              this.a.transact(4, localParcel1, localParcel2, 0);
              localParcel2.readException();
              int i = localParcel2.readInt();
              if (i != 0) {
                return bool;
              }
            }
            else
            {
              localParcel1.writeInt(0);
              continue;
            }
            bool = false;
          }
          finally
          {
            localParcel2.recycle();
            localParcel1.recycle();
          }
        }
      }
      
      public IBinder asBinder()
      {
        return this.a;
      }
      
      public void b()
      {
        Parcel localParcel1 = Parcel.obtain();
        Parcel localParcel2 = Parcel.obtain();
        try
        {
          localParcel1.writeInterfaceToken("com.google.android.gms.ads.internal.client.IAdManager");
          this.a.transact(2, localParcel1, localParcel2, 0);
          localParcel2.readException();
          return;
        }
        finally
        {
          localParcel2.recycle();
          localParcel1.recycle();
        }
      }
      
      public boolean c()
      {
        boolean bool = false;
        Parcel localParcel1 = Parcel.obtain();
        Parcel localParcel2 = Parcel.obtain();
        try
        {
          localParcel1.writeInterfaceToken("com.google.android.gms.ads.internal.client.IAdManager");
          this.a.transact(3, localParcel1, localParcel2, 0);
          localParcel2.readException();
          int i = localParcel2.readInt();
          if (i != 0) {
            bool = true;
          }
          return bool;
        }
        finally
        {
          localParcel2.recycle();
          localParcel1.recycle();
        }
      }
      
      public void c_()
      {
        Parcel localParcel1 = Parcel.obtain();
        Parcel localParcel2 = Parcel.obtain();
        try
        {
          localParcel1.writeInterfaceToken("com.google.android.gms.ads.internal.client.IAdManager");
          this.a.transact(6, localParcel1, localParcel2, 0);
          localParcel2.readException();
          return;
        }
        finally
        {
          localParcel2.recycle();
          localParcel1.recycle();
        }
      }
      
      public void d()
      {
        Parcel localParcel1 = Parcel.obtain();
        Parcel localParcel2 = Parcel.obtain();
        try
        {
          localParcel1.writeInterfaceToken("com.google.android.gms.ads.internal.client.IAdManager");
          this.a.transact(5, localParcel1, localParcel2, 0);
          localParcel2.readException();
          return;
        }
        finally
        {
          localParcel2.recycle();
          localParcel1.recycle();
        }
      }
      
      public void f()
      {
        Parcel localParcel1 = Parcel.obtain();
        Parcel localParcel2 = Parcel.obtain();
        try
        {
          localParcel1.writeInterfaceToken("com.google.android.gms.ads.internal.client.IAdManager");
          this.a.transact(9, localParcel1, localParcel2, 0);
          localParcel2.readException();
          return;
        }
        finally
        {
          localParcel2.recycle();
          localParcel1.recycle();
        }
      }
      
      public void g_()
      {
        Parcel localParcel1 = Parcel.obtain();
        Parcel localParcel2 = Parcel.obtain();
        try
        {
          localParcel1.writeInterfaceToken("com.google.android.gms.ads.internal.client.IAdManager");
          this.a.transact(10, localParcel1, localParcel2, 0);
          localParcel2.readException();
          return;
        }
        finally
        {
          localParcel2.recycle();
          localParcel1.recycle();
        }
      }
      
      public void h()
      {
        Parcel localParcel1 = Parcel.obtain();
        Parcel localParcel2 = Parcel.obtain();
        try
        {
          localParcel1.writeInterfaceToken("com.google.android.gms.ads.internal.client.IAdManager");
          this.a.transact(11, localParcel1, localParcel2, 0);
          localParcel2.readException();
          return;
        }
        finally
        {
          localParcel2.recycle();
          localParcel1.recycle();
        }
      }
      
      /* Error */
      public AdSizeParcel i()
      {
        // Byte code:
        //   0: invokestatic 25	android/os/Parcel:obtain	()Landroid/os/Parcel;
        //   3: astore_2
        //   4: invokestatic 25	android/os/Parcel:obtain	()Landroid/os/Parcel;
        //   7: astore_3
        //   8: aload_2
        //   9: ldc 27
        //   11: invokevirtual 31	android/os/Parcel:writeInterfaceToken	(Ljava/lang/String;)V
        //   14: aload_0
        //   15: getfield 17	com/google/android/gms/ads/internal/client/ak$a$a:a	Landroid/os/IBinder;
        //   18: bipush 12
        //   20: aload_2
        //   21: aload_3
        //   22: iconst_0
        //   23: invokeinterface 37 5 0
        //   28: pop
        //   29: aload_3
        //   30: invokevirtual 40	android/os/Parcel:readException	()V
        //   33: aload_3
        //   34: invokevirtual 116	android/os/Parcel:readInt	()I
        //   37: ifeq +24 -> 61
        //   40: getstatic 130	com/google/android/gms/ads/internal/client/AdSizeParcel:CREATOR	Lcom/google/android/gms/ads/internal/client/z;
        //   43: aload_3
        //   44: invokevirtual 136	com/google/android/gms/ads/internal/client/z:createFromParcel	(Landroid/os/Parcel;)Ljava/lang/Object;
        //   47: checkcast 59	com/google/android/gms/ads/internal/client/AdSizeParcel
        //   50: astore_1
        //   51: aload_3
        //   52: invokevirtual 52	android/os/Parcel:recycle	()V
        //   55: aload_2
        //   56: invokevirtual 52	android/os/Parcel:recycle	()V
        //   59: aload_1
        //   60: areturn
        //   61: aconst_null
        //   62: astore_1
        //   63: goto -12 -> 51
        //   66: astore_1
        //   67: aload_3
        //   68: invokevirtual 52	android/os/Parcel:recycle	()V
        //   71: aload_2
        //   72: invokevirtual 52	android/os/Parcel:recycle	()V
        //   75: aload_1
        //   76: athrow
        // Local variable table:
        //   start	length	slot	name	signature
        //   0	77	0	this	a
        //   50	13	1	localAdSizeParcel	AdSizeParcel
        //   66	10	1	localObject	Object
        //   3	69	2	localParcel1	Parcel
        //   7	61	3	localParcel2	Parcel
        // Exception table:
        //   from	to	target	type
        //   8	51	66	finally
      }
      
      public String j()
      {
        Parcel localParcel1 = Parcel.obtain();
        Parcel localParcel2 = Parcel.obtain();
        try
        {
          localParcel1.writeInterfaceToken("com.google.android.gms.ads.internal.client.IAdManager");
          this.a.transact(18, localParcel1, localParcel2, 0);
          localParcel2.readException();
          String str = localParcel2.readString();
          return str;
        }
        finally
        {
          localParcel2.recycle();
          localParcel1.recycle();
        }
      }
      
      public boolean k()
      {
        boolean bool = false;
        Parcel localParcel1 = Parcel.obtain();
        Parcel localParcel2 = Parcel.obtain();
        try
        {
          localParcel1.writeInterfaceToken("com.google.android.gms.ads.internal.client.IAdManager");
          this.a.transact(23, localParcel1, localParcel2, 0);
          localParcel2.readException();
          int i = localParcel2.readInt();
          if (i != 0) {
            bool = true;
          }
          return bool;
        }
        finally
        {
          localParcel2.recycle();
          localParcel1.recycle();
        }
      }
      
      public c l()
      {
        Parcel localParcel1 = Parcel.obtain();
        Parcel localParcel2 = Parcel.obtain();
        try
        {
          localParcel1.writeInterfaceToken("com.google.android.gms.ads.internal.client.IAdManager");
          this.a.transact(26, localParcel1, localParcel2, 0);
          localParcel2.readException();
          c localc = c.a.a(localParcel2.readStrongBinder());
          return localc;
        }
        finally
        {
          localParcel2.recycle();
          localParcel1.recycle();
        }
      }
    }
  }
}


/* Location:              /Users/andi/Downloads/dex2jar-2.0/classes-dex2jar.jar!/com/google/android/gms/ads/internal/client/ak.class
 * Java compiler version: 6 (50.0)
 * JD-Core Version:       0.7.1
 */