package com.b.a.b;

import android.graphics.Bitmap;
import android.os.Handler;
import java.io.File;
import java.io.IOException;
import java.io.InputStream;
import java.util.concurrent.atomic.AtomicBoolean;

final class h
  implements com.b.a.c.c.a, Runnable
{
  private static final String f = "ImageLoader is paused. Waiting...  [%s]";
  private static final String g = ".. Resume loading [%s]";
  private static final String h = "Delay %d ms before loading...  [%s]";
  private static final String i = "Start display image task [%s]";
  private static final String j = "Image already is loading. Waiting... [%s]";
  private static final String k = "...Get cached bitmap from memory after waiting. [%s]";
  private static final String l = "Load image from network [%s]";
  private static final String m = "Load image from disk cache [%s]";
  private static final String n = "Resize image in disk cache [%s]";
  private static final String o = "PreProcess image before caching in memory [%s]";
  private static final String p = "PostProcess image before displaying [%s]";
  private static final String q = "Cache image in memory [%s]";
  private static final String r = "Cache image on disk [%s]";
  private static final String s = "Process image before cache on disk [%s]";
  private static final String t = "ImageAware is reused for another image. Task is cancelled. [%s]";
  private static final String u = "ImageAware was collected by GC. Task is cancelled. [%s]";
  private static final String v = "Task was interrupted [%s]";
  private static final String w = "No stream for image [%s]";
  private static final String x = "Pre-processor returned null [%s]";
  private static final String y = "Post-processor returned null [%s]";
  private static final String z = "Bitmap processor for disk cache returned null [%s]";
  private final f A;
  private final g B;
  private final Handler C;
  private final e D;
  private final com.b.a.b.d.b E;
  private final com.b.a.b.d.b F;
  private final com.b.a.b.d.b G;
  private final com.b.a.b.b.b H;
  private final String I;
  private final com.b.a.b.a.e J;
  private final boolean K;
  private com.b.a.b.a.f L = com.b.a.b.a.f.a;
  final String a;
  final com.b.a.b.e.a b;
  final c c;
  final com.b.a.b.f.a d;
  final com.b.a.b.f.b e;
  
  public h(f paramf, g paramg, Handler paramHandler)
  {
    this.A = paramf;
    this.B = paramg;
    this.C = paramHandler;
    this.D = paramf.a;
    this.E = this.D.p;
    this.F = this.D.s;
    this.G = this.D.t;
    this.H = this.D.q;
    this.a = paramg.a;
    this.I = paramg.b;
    this.b = paramg.c;
    this.J = paramg.d;
    this.c = paramg.e;
    this.d = paramg.f;
    this.e = paramg.g;
    this.K = this.c.s();
  }
  
  private Bitmap a(String paramString)
  {
    com.b.a.b.a.h localh = this.b.c();
    paramString = new com.b.a.b.b.c(this.I, paramString, this.a, this.J, localh, h(), this.c);
    return this.H.a(paramString);
  }
  
  private void a(final com.b.a.b.a.b.a parama, final Throwable paramThrowable)
  {
    if ((this.K) || (p()) || (j())) {
      return;
    }
    a(new Runnable()
    {
      public void run()
      {
        if (h.this.c.c()) {
          h.this.b.a(h.this.c.c(h.a(h.this).a));
        }
        h.this.d.a(h.this.a, h.this.b.d(), new com.b.a.b.a.b(parama, paramThrowable));
      }
    }, false, this.C, this.A);
  }
  
  static void a(Runnable paramRunnable, boolean paramBoolean, Handler paramHandler, f paramf)
  {
    if (paramBoolean)
    {
      paramRunnable.run();
      return;
    }
    if (paramHandler == null)
    {
      paramf.a(paramRunnable);
      return;
    }
    paramHandler.post(paramRunnable);
  }
  
  private boolean b()
  {
    AtomicBoolean localAtomicBoolean = this.A.d();
    if (localAtomicBoolean.get()) {}
    synchronized (this.A.e())
    {
      if (localAtomicBoolean.get()) {
        com.b.a.c.d.a("ImageLoader is paused. Waiting...  [%s]", new Object[] { this.I });
      }
      try
      {
        this.A.e().wait();
        com.b.a.c.d.a(".. Resume loading [%s]", new Object[] { this.I });
        return j();
      }
      catch (InterruptedException localInterruptedException)
      {
        com.b.a.c.d.d("Task was interrupted [%s]", new Object[] { this.I });
        return true;
      }
    }
  }
  
  private boolean b(int paramInt1, int paramInt2)
  {
    Object localObject1 = this.D.o.a(this.a);
    if ((localObject1 != null) && (((File)localObject1).exists()))
    {
      Object localObject2 = new com.b.a.b.a.e(paramInt1, paramInt2);
      c localc = new c.a().a(this.c).a(com.b.a.b.a.d.d).d();
      localObject1 = new com.b.a.b.b.c(this.I, com.b.a.b.d.b.a.c.b(((File)localObject1).getAbsolutePath()), this.a, (com.b.a.b.a.e)localObject2, com.b.a.b.a.h.a, h(), localc);
      localObject2 = this.H.a((com.b.a.b.b.c)localObject1);
      localObject1 = localObject2;
      if (localObject2 != null)
      {
        localObject1 = localObject2;
        if (this.D.f != null)
        {
          com.b.a.c.d.a("Process image before cache on disk [%s]", new Object[] { this.I });
          localObject2 = this.D.f.a((Bitmap)localObject2);
          localObject1 = localObject2;
          if (localObject2 == null)
          {
            com.b.a.c.d.d("Bitmap processor for disk cache returned null [%s]", new Object[] { this.I });
            localObject1 = localObject2;
          }
        }
      }
      if (localObject1 != null)
      {
        boolean bool = this.D.o.a(this.a, (Bitmap)localObject1);
        ((Bitmap)localObject1).recycle();
        return bool;
      }
    }
    return false;
  }
  
  private boolean c()
  {
    if (this.c.f())
    {
      com.b.a.c.d.a("Delay %d ms before loading...  [%s]", new Object[] { Integer.valueOf(this.c.l()), this.I });
      try
      {
        Thread.sleep(this.c.l());
        return j();
      }
      catch (InterruptedException localInterruptedException)
      {
        com.b.a.c.d.d("Task was interrupted [%s]", new Object[] { this.I });
        return true;
      }
    }
    return false;
  }
  
  private boolean c(final int paramInt1, final int paramInt2)
  {
    if ((p()) || (j())) {
      return false;
    }
    if (this.e != null) {
      a(new Runnable()
      {
        public void run()
        {
          h.this.e.a(h.this.a, h.this.b.d(), paramInt1, paramInt2);
        }
      }, false, this.C, this.A);
    }
    return true;
  }
  
  private Bitmap d()
  {
    for (;;)
    {
      try
      {
        Object localObject1 = this.D.o.a(this.a);
        Object localObject3;
        Object localObject4;
        Object localObject5;
        Object localObject6;
        if ((localObject1 != null) && (((File)localObject1).exists()) && (((File)localObject1).length() > 0L))
        {
          com.b.a.c.d.a("Load image from disk cache [%s]", new Object[] { this.I });
          this.L = com.b.a.b.a.f.b;
          i();
          localObject1 = a(com.b.a.b.d.b.a.c.b(((File)localObject1).getAbsolutePath()));
          if (localObject1 != null)
          {
            localObject3 = localObject1;
            localObject4 = localObject1;
            localObject5 = localObject1;
            localObject6 = localObject1;
          }
        }
        Object localObject7;
        String str;
        File localFile;
        Object localObject2 = null;
      }
      catch (IllegalStateException localIllegalStateException1)
      {
        try
        {
          if (((Bitmap)localObject1).getWidth() > 0)
          {
            localObject7 = localObject1;
            localObject3 = localObject1;
            localObject4 = localObject1;
            localObject5 = localObject1;
            localObject6 = localObject1;
            if (((Bitmap)localObject1).getHeight() > 0) {}
          }
          else
          {
            localObject3 = localObject1;
            localObject4 = localObject1;
            localObject5 = localObject1;
            localObject6 = localObject1;
            com.b.a.c.d.a("Load image from network [%s]", new Object[] { this.I });
            localObject3 = localObject1;
            localObject4 = localObject1;
            localObject5 = localObject1;
            localObject6 = localObject1;
            this.L = com.b.a.b.a.f.a;
            localObject3 = localObject1;
            localObject4 = localObject1;
            localObject5 = localObject1;
            localObject6 = localObject1;
            str = this.a;
            localObject7 = str;
            localObject3 = localObject1;
            localObject4 = localObject1;
            localObject5 = localObject1;
            localObject6 = localObject1;
            if (this.c.i())
            {
              localObject7 = str;
              localObject3 = localObject1;
              localObject4 = localObject1;
              localObject5 = localObject1;
              localObject6 = localObject1;
              if (e())
              {
                localObject3 = localObject1;
                localObject4 = localObject1;
                localObject5 = localObject1;
                localObject6 = localObject1;
                localFile = this.D.o.a(this.a);
                localObject7 = str;
                if (localFile != null)
                {
                  localObject3 = localObject1;
                  localObject4 = localObject1;
                  localObject5 = localObject1;
                  localObject6 = localObject1;
                  localObject7 = com.b.a.b.d.b.a.c.b(localFile.getAbsolutePath());
                }
              }
            }
            localObject3 = localObject1;
            localObject4 = localObject1;
            localObject5 = localObject1;
            localObject6 = localObject1;
            i();
            localObject3 = localObject1;
            localObject4 = localObject1;
            localObject5 = localObject1;
            localObject6 = localObject1;
            localObject1 = a((String)localObject7);
            if (localObject1 != null)
            {
              localObject3 = localObject1;
              localObject4 = localObject1;
              localObject5 = localObject1;
              localObject6 = localObject1;
              if (((Bitmap)localObject1).getWidth() > 0)
              {
                localObject7 = localObject1;
                localObject3 = localObject1;
                localObject4 = localObject1;
                localObject5 = localObject1;
                localObject6 = localObject1;
                if (((Bitmap)localObject1).getHeight() > 0) {
                  continue;
                }
              }
            }
            localObject3 = localObject1;
            localObject4 = localObject1;
            localObject5 = localObject1;
            localObject6 = localObject1;
            a(com.b.a.b.a.b.a.b, null);
            localObject7 = localObject1;
          }
          return (Bitmap)localObject7;
        }
        catch (Throwable localThrowable2)
        {
          continue;
        }
        catch (OutOfMemoryError localOutOfMemoryError2)
        {
          continue;
        }
        catch (IOException localIOException2)
        {
          continue;
        }
        catch (IllegalStateException localIllegalStateException2)
        {
          continue;
        }
        localIllegalStateException1 = localIllegalStateException1;
        localObject6 = null;
        a(com.b.a.b.a.b.a.c, null);
        return (Bitmap)localObject6;
      }
      catch (a locala)
      {
        throw locala;
      }
      catch (IOException localIOException1)
      {
        localObject5 = null;
        com.b.a.c.d.a(localIOException1);
        a(com.b.a.b.a.b.a.a, localIOException1);
        return (Bitmap)localObject5;
      }
      catch (OutOfMemoryError localOutOfMemoryError1)
      {
        localObject4 = null;
        com.b.a.c.d.a(localOutOfMemoryError1);
        a(com.b.a.b.a.b.a.d, localOutOfMemoryError1);
        return (Bitmap)localObject4;
      }
      catch (Throwable localThrowable1)
      {
        localObject3 = null;
        com.b.a.c.d.a(localThrowable1);
        a(com.b.a.b.a.b.a.e, localThrowable1);
        return (Bitmap)localObject3;
      }
    }
  }
  
  private boolean e()
  {
    com.b.a.c.d.a("Cache image on disk [%s]", new Object[] { this.I });
    try
    {
      boolean bool = f();
      if (bool)
      {
        int i1 = this.D.d;
        int i2 = this.D.e;
        if ((i1 > 0) || (i2 > 0))
        {
          com.b.a.c.d.a("Resize image in disk cache [%s]", new Object[] { this.I });
          b(i1, i2);
        }
      }
      return bool;
    }
    catch (IOException localIOException)
    {
      com.b.a.c.d.a(localIOException);
    }
    return false;
  }
  
  private boolean f()
  {
    InputStream localInputStream = h().a(this.a, this.c.n());
    if (localInputStream == null)
    {
      com.b.a.c.d.d("No stream for image [%s]", new Object[] { this.I });
      return false;
    }
    try
    {
      boolean bool = this.D.o.a(this.a, localInputStream, this);
      return bool;
    }
    finally
    {
      com.b.a.c.c.a(localInputStream);
    }
  }
  
  private void g()
  {
    if ((this.K) || (p())) {
      return;
    }
    a(new Runnable()
    {
      public void run()
      {
        h.this.d.b(h.this.a, h.this.b.d());
      }
    }, false, this.C, this.A);
  }
  
  private com.b.a.b.d.b h()
  {
    if (this.A.f()) {
      return this.F;
    }
    if (this.A.g()) {
      return this.G;
    }
    return this.E;
  }
  
  private void i()
  {
    k();
    m();
  }
  
  private boolean j()
  {
    return (l()) || (n());
  }
  
  private void k()
  {
    if (l()) {
      throw new a();
    }
  }
  
  private boolean l()
  {
    if (this.b.e())
    {
      com.b.a.c.d.a("ImageAware was collected by GC. Task is cancelled. [%s]", new Object[] { this.I });
      return true;
    }
    return false;
  }
  
  private void m()
  {
    if (n()) {
      throw new a();
    }
  }
  
  private boolean n()
  {
    String str = this.A.a(this.b);
    if (!this.I.equals(str)) {}
    for (int i1 = 1; i1 != 0; i1 = 0)
    {
      com.b.a.c.d.a("ImageAware is reused for another image. Task is cancelled. [%s]", new Object[] { this.I });
      return true;
    }
    return false;
  }
  
  private void o()
  {
    if (p()) {
      throw new a();
    }
  }
  
  private boolean p()
  {
    if (Thread.interrupted())
    {
      com.b.a.c.d.a("Task was interrupted [%s]", new Object[] { this.I });
      return true;
    }
    return false;
  }
  
  String a()
  {
    return this.a;
  }
  
  public boolean a(int paramInt1, int paramInt2)
  {
    return (this.K) || (c(paramInt1, paramInt2));
  }
  
  /* Error */
  public void run()
  {
    // Byte code:
    //   0: aload_0
    //   1: invokespecial 444	com/b/a/b/h:b	()Z
    //   4: ifeq +4 -> 8
    //   7: return
    //   8: aload_0
    //   9: invokespecial 446	com/b/a/b/h:c	()Z
    //   12: ifne -5 -> 7
    //   15: aload_0
    //   16: getfield 125	com/b/a/b/h:B	Lcom/b/a/b/g;
    //   19: getfield 449	com/b/a/b/g:h	Ljava/util/concurrent/locks/ReentrantLock;
    //   22: astore_3
    //   23: ldc 30
    //   25: iconst_1
    //   26: anewarray 4	java/lang/Object
    //   29: dup
    //   30: iconst_0
    //   31: aload_0
    //   32: getfield 160	com/b/a/b/h:I	Ljava/lang/String;
    //   35: aastore
    //   36: invokestatic 249	com/b/a/c/d:a	(Ljava/lang/String;[Ljava/lang/Object;)V
    //   39: aload_3
    //   40: invokevirtual 454	java/util/concurrent/locks/ReentrantLock:isLocked	()Z
    //   43: ifeq +19 -> 62
    //   46: ldc 33
    //   48: iconst_1
    //   49: anewarray 4	java/lang/Object
    //   52: dup
    //   53: iconst_0
    //   54: aload_0
    //   55: getfield 160	com/b/a/b/h:I	Ljava/lang/String;
    //   58: aastore
    //   59: invokestatic 249	com/b/a/c/d:a	(Ljava/lang/String;[Ljava/lang/Object;)V
    //   62: aload_3
    //   63: invokevirtual 457	java/util/concurrent/locks/ReentrantLock:lock	()V
    //   66: aload_0
    //   67: invokespecial 360	com/b/a/b/h:i	()V
    //   70: aload_0
    //   71: getfield 133	com/b/a/b/h:D	Lcom/b/a/b/e;
    //   74: getfield 460	com/b/a/b/e:n	Lcom/b/a/a/b/c;
    //   77: aload_0
    //   78: getfield 160	com/b/a/b/h:I	Ljava/lang/String;
    //   81: invokeinterface 463 2 0
    //   86: astore_2
    //   87: aload_2
    //   88: ifnull +10 -> 98
    //   91: aload_2
    //   92: invokevirtual 466	android/graphics/Bitmap:isRecycled	()Z
    //   95: ifeq +265 -> 360
    //   98: aload_0
    //   99: invokespecial 468	com/b/a/b/h:d	()Landroid/graphics/Bitmap;
    //   102: astore_2
    //   103: aload_2
    //   104: ifnonnull +8 -> 112
    //   107: aload_3
    //   108: invokevirtual 471	java/util/concurrent/locks/ReentrantLock:unlock	()V
    //   111: return
    //   112: aload_0
    //   113: invokespecial 360	com/b/a/b/h:i	()V
    //   116: aload_0
    //   117: invokespecial 473	com/b/a/b/h:o	()V
    //   120: aload_2
    //   121: astore_1
    //   122: aload_0
    //   123: getfield 172	com/b/a/b/h:c	Lcom/b/a/b/c;
    //   126: invokevirtual 475	com/b/a/b/c:d	()Z
    //   129: ifeq +57 -> 186
    //   132: ldc 48
    //   134: iconst_1
    //   135: anewarray 4	java/lang/Object
    //   138: dup
    //   139: iconst_0
    //   140: aload_0
    //   141: getfield 160	com/b/a/b/h:I	Ljava/lang/String;
    //   144: aastore
    //   145: invokestatic 249	com/b/a/c/d:a	(Ljava/lang/String;[Ljava/lang/Object;)V
    //   148: aload_0
    //   149: getfield 172	com/b/a/b/h:c	Lcom/b/a/b/c;
    //   152: invokevirtual 478	com/b/a/b/c:o	()Lcom/b/a/b/g/a;
    //   155: aload_2
    //   156: invokeinterface 315 2 0
    //   161: astore_2
    //   162: aload_2
    //   163: astore_1
    //   164: aload_2
    //   165: ifnonnull +21 -> 186
    //   168: ldc 75
    //   170: iconst_1
    //   171: anewarray 4	java/lang/Object
    //   174: dup
    //   175: iconst_0
    //   176: aload_0
    //   177: getfield 160	com/b/a/b/h:I	Ljava/lang/String;
    //   180: aastore
    //   181: invokestatic 254	com/b/a/c/d:d	(Ljava/lang/String;[Ljava/lang/Object;)V
    //   184: aload_2
    //   185: astore_1
    //   186: aload_1
    //   187: astore_2
    //   188: aload_1
    //   189: ifnull +51 -> 240
    //   192: aload_1
    //   193: astore_2
    //   194: aload_0
    //   195: getfield 172	com/b/a/b/h:c	Lcom/b/a/b/c;
    //   198: invokevirtual 480	com/b/a/b/c:h	()Z
    //   201: ifeq +39 -> 240
    //   204: ldc 54
    //   206: iconst_1
    //   207: anewarray 4	java/lang/Object
    //   210: dup
    //   211: iconst_0
    //   212: aload_0
    //   213: getfield 160	com/b/a/b/h:I	Ljava/lang/String;
    //   216: aastore
    //   217: invokestatic 249	com/b/a/c/d:a	(Ljava/lang/String;[Ljava/lang/Object;)V
    //   220: aload_0
    //   221: getfield 133	com/b/a/b/h:D	Lcom/b/a/b/e;
    //   224: getfield 460	com/b/a/b/e:n	Lcom/b/a/a/b/c;
    //   227: aload_0
    //   228: getfield 160	com/b/a/b/h:I	Ljava/lang/String;
    //   231: aload_1
    //   232: invokeinterface 481 3 0
    //   237: pop
    //   238: aload_1
    //   239: astore_2
    //   240: aload_2
    //   241: astore_1
    //   242: aload_2
    //   243: ifnull +69 -> 312
    //   246: aload_2
    //   247: astore_1
    //   248: aload_0
    //   249: getfield 172	com/b/a/b/h:c	Lcom/b/a/b/c;
    //   252: invokevirtual 482	com/b/a/b/c:e	()Z
    //   255: ifeq +57 -> 312
    //   258: ldc 51
    //   260: iconst_1
    //   261: anewarray 4	java/lang/Object
    //   264: dup
    //   265: iconst_0
    //   266: aload_0
    //   267: getfield 160	com/b/a/b/h:I	Ljava/lang/String;
    //   270: aastore
    //   271: invokestatic 249	com/b/a/c/d:a	(Ljava/lang/String;[Ljava/lang/Object;)V
    //   274: aload_0
    //   275: getfield 172	com/b/a/b/h:c	Lcom/b/a/b/c;
    //   278: invokevirtual 484	com/b/a/b/c:p	()Lcom/b/a/b/g/a;
    //   281: aload_2
    //   282: invokeinterface 315 2 0
    //   287: astore_2
    //   288: aload_2
    //   289: astore_1
    //   290: aload_2
    //   291: ifnonnull +21 -> 312
    //   294: ldc 78
    //   296: iconst_1
    //   297: anewarray 4	java/lang/Object
    //   300: dup
    //   301: iconst_0
    //   302: aload_0
    //   303: getfield 160	com/b/a/b/h:I	Ljava/lang/String;
    //   306: aastore
    //   307: invokestatic 254	com/b/a/c/d:d	(Ljava/lang/String;[Ljava/lang/Object;)V
    //   310: aload_2
    //   311: astore_1
    //   312: aload_0
    //   313: invokespecial 360	com/b/a/b/h:i	()V
    //   316: aload_0
    //   317: invokespecial 473	com/b/a/b/h:o	()V
    //   320: aload_3
    //   321: invokevirtual 471	java/util/concurrent/locks/ReentrantLock:unlock	()V
    //   324: new 486	com/b/a/b/b
    //   327: dup
    //   328: aload_1
    //   329: aload_0
    //   330: getfield 125	com/b/a/b/h:B	Lcom/b/a/b/g;
    //   333: aload_0
    //   334: getfield 123	com/b/a/b/h:A	Lcom/b/a/b/f;
    //   337: aload_0
    //   338: getfield 121	com/b/a/b/h:L	Lcom/b/a/b/a/f;
    //   341: invokespecial 489	com/b/a/b/b:<init>	(Landroid/graphics/Bitmap;Lcom/b/a/b/g;Lcom/b/a/b/f;Lcom/b/a/b/a/f;)V
    //   344: aload_0
    //   345: getfield 187	com/b/a/b/h:K	Z
    //   348: aload_0
    //   349: getfield 127	com/b/a/b/h:C	Landroid/os/Handler;
    //   352: aload_0
    //   353: getfield 123	com/b/a/b/h:A	Lcom/b/a/b/f;
    //   356: invokestatic 219	com/b/a/b/h:a	(Ljava/lang/Runnable;ZLandroid/os/Handler;Lcom/b/a/b/f;)V
    //   359: return
    //   360: aload_0
    //   361: getstatic 491	com/b/a/b/a/f:c	Lcom/b/a/b/a/f;
    //   364: putfield 121	com/b/a/b/h:L	Lcom/b/a/b/a/f;
    //   367: ldc 36
    //   369: iconst_1
    //   370: anewarray 4	java/lang/Object
    //   373: dup
    //   374: iconst_0
    //   375: aload_0
    //   376: getfield 160	com/b/a/b/h:I	Ljava/lang/String;
    //   379: aastore
    //   380: invokestatic 249	com/b/a/c/d:a	(Ljava/lang/String;[Ljava/lang/Object;)V
    //   383: goto -143 -> 240
    //   386: astore_1
    //   387: aload_0
    //   388: invokespecial 493	com/b/a/b/h:g	()V
    //   391: aload_3
    //   392: invokevirtual 471	java/util/concurrent/locks/ReentrantLock:unlock	()V
    //   395: return
    //   396: astore_1
    //   397: aload_3
    //   398: invokevirtual 471	java/util/concurrent/locks/ReentrantLock:unlock	()V
    //   401: aload_1
    //   402: athrow
    // Local variable table:
    //   start	length	slot	name	signature
    //   0	403	0	this	h
    //   121	208	1	localObject1	Object
    //   386	1	1	locala	a
    //   396	6	1	localObject2	Object
    //   86	225	2	localObject3	Object
    //   22	376	3	localReentrantLock	java.util.concurrent.locks.ReentrantLock
    // Exception table:
    //   from	to	target	type
    //   66	87	386	com/b/a/b/h$a
    //   91	98	386	com/b/a/b/h$a
    //   98	103	386	com/b/a/b/h$a
    //   112	120	386	com/b/a/b/h$a
    //   122	162	386	com/b/a/b/h$a
    //   168	184	386	com/b/a/b/h$a
    //   194	238	386	com/b/a/b/h$a
    //   248	288	386	com/b/a/b/h$a
    //   294	310	386	com/b/a/b/h$a
    //   312	320	386	com/b/a/b/h$a
    //   360	383	386	com/b/a/b/h$a
    //   66	87	396	finally
    //   91	98	396	finally
    //   98	103	396	finally
    //   112	120	396	finally
    //   122	162	396	finally
    //   168	184	396	finally
    //   194	238	396	finally
    //   248	288	396	finally
    //   294	310	396	finally
    //   312	320	396	finally
    //   360	383	396	finally
    //   387	391	396	finally
  }
  
  class a
    extends Exception
  {
    a() {}
  }
}


/* Location:              /Users/andi/Downloads/dex2jar-2.0/classes-dex2jar.jar!/com/b/a/b/h.class
 * Java compiler version: 6 (50.0)
 * JD-Core Version:       0.7.1
 */