package com.google.android.gms.cast.framework;

import android.os.Binder;
import android.os.IBinder;
import android.os.IInterface;
import android.os.Parcel;
import com.google.android.gms.c.e;
import com.google.android.gms.c.e.a;

public abstract interface ab
  extends IInterface
{
  public abstract int a();
  
  public abstract void a(e parame);
  
  public abstract void a(e parame, int paramInt);
  
  public abstract void a(e parame, String paramString);
  
  public abstract void a(e parame, boolean paramBoolean);
  
  public abstract e b();
  
  public abstract void b(e parame);
  
  public abstract void b(e parame, int paramInt);
  
  public abstract void b(e parame, String paramString);
  
  public abstract void c(e parame, int paramInt);
  
  public abstract void d(e parame, int paramInt);
  
  public static abstract class a
    extends Binder
    implements ab
  {
    public a()
    {
      attachInterface(this, "com.google.android.gms.cast.framework.ISessionManagerListener");
    }
    
    public static ab a(IBinder paramIBinder)
    {
      if (paramIBinder == null) {
        return null;
      }
      IInterface localIInterface = paramIBinder.queryLocalInterface("com.google.android.gms.cast.framework.ISessionManagerListener");
      if ((localIInterface != null) && ((localIInterface instanceof ab))) {
        return (ab)localIInterface;
      }
      return new a(paramIBinder);
    }
    
    public IBinder asBinder()
    {
      return this;
    }
    
    public boolean onTransact(int paramInt1, Parcel paramParcel1, Parcel paramParcel2, int paramInt2)
    {
      switch (paramInt1)
      {
      default: 
        return super.onTransact(paramInt1, paramParcel1, paramParcel2, paramInt2);
      case 1598968902: 
        paramParcel2.writeString("com.google.android.gms.cast.framework.ISessionManagerListener");
        return true;
      case 11: 
        paramParcel1.enforceInterface("com.google.android.gms.cast.framework.ISessionManagerListener");
        paramInt1 = a();
        paramParcel2.writeNoException();
        paramParcel2.writeInt(paramInt1);
        return true;
      case 1: 
        paramParcel1.enforceInterface("com.google.android.gms.cast.framework.ISessionManagerListener");
        paramParcel1 = b();
        paramParcel2.writeNoException();
        if (paramParcel1 != null) {}
        for (paramParcel1 = paramParcel1.asBinder();; paramParcel1 = null)
        {
          paramParcel2.writeStrongBinder(paramParcel1);
          return true;
        }
      case 2: 
        paramParcel1.enforceInterface("com.google.android.gms.cast.framework.ISessionManagerListener");
        a(e.a.a(paramParcel1.readStrongBinder()));
        paramParcel2.writeNoException();
        return true;
      case 3: 
        paramParcel1.enforceInterface("com.google.android.gms.cast.framework.ISessionManagerListener");
        a(e.a.a(paramParcel1.readStrongBinder()), paramParcel1.readString());
        paramParcel2.writeNoException();
        return true;
      case 4: 
        paramParcel1.enforceInterface("com.google.android.gms.cast.framework.ISessionManagerListener");
        a(e.a.a(paramParcel1.readStrongBinder()), paramParcel1.readInt());
        paramParcel2.writeNoException();
        return true;
      case 5: 
        paramParcel1.enforceInterface("com.google.android.gms.cast.framework.ISessionManagerListener");
        b(e.a.a(paramParcel1.readStrongBinder()));
        paramParcel2.writeNoException();
        return true;
      case 6: 
        paramParcel1.enforceInterface("com.google.android.gms.cast.framework.ISessionManagerListener");
        b(e.a.a(paramParcel1.readStrongBinder()), paramParcel1.readInt());
        paramParcel2.writeNoException();
        return true;
      case 7: 
        paramParcel1.enforceInterface("com.google.android.gms.cast.framework.ISessionManagerListener");
        b(e.a.a(paramParcel1.readStrongBinder()), paramParcel1.readString());
        paramParcel2.writeNoException();
        return true;
      case 8: 
        paramParcel1.enforceInterface("com.google.android.gms.cast.framework.ISessionManagerListener");
        e locale = e.a.a(paramParcel1.readStrongBinder());
        if (paramParcel1.readInt() != 0) {}
        for (boolean bool = true;; bool = false)
        {
          a(locale, bool);
          paramParcel2.writeNoException();
          return true;
        }
      case 9: 
        paramParcel1.enforceInterface("com.google.android.gms.cast.framework.ISessionManagerListener");
        c(e.a.a(paramParcel1.readStrongBinder()), paramParcel1.readInt());
        paramParcel2.writeNoException();
        return true;
      }
      paramParcel1.enforceInterface("com.google.android.gms.cast.framework.ISessionManagerListener");
      d(e.a.a(paramParcel1.readStrongBinder()), paramParcel1.readInt());
      paramParcel2.writeNoException();
      return true;
    }
    
    private static class a
      implements ab
    {
      private IBinder a;
      
      a(IBinder paramIBinder)
      {
        this.a = paramIBinder;
      }
      
      public int a()
      {
        Parcel localParcel1 = Parcel.obtain();
        Parcel localParcel2 = Parcel.obtain();
        try
        {
          localParcel1.writeInterfaceToken("com.google.android.gms.cast.framework.ISessionManagerListener");
          this.a.transact(11, localParcel1, localParcel2, 0);
          localParcel2.readException();
          int i = localParcel2.readInt();
          return i;
        }
        finally
        {
          localParcel2.recycle();
          localParcel1.recycle();
        }
      }
      
      /* Error */
      public void a(e parame)
      {
        // Byte code:
        //   0: invokestatic 25	android/os/Parcel:obtain	()Landroid/os/Parcel;
        //   3: astore_2
        //   4: invokestatic 25	android/os/Parcel:obtain	()Landroid/os/Parcel;
        //   7: astore_3
        //   8: aload_2
        //   9: ldc 27
        //   11: invokevirtual 31	android/os/Parcel:writeInterfaceToken	(Ljava/lang/String;)V
        //   14: aload_1
        //   15: ifnull +42 -> 57
        //   18: aload_1
        //   19: invokeinterface 53 1 0
        //   24: astore_1
        //   25: aload_2
        //   26: aload_1
        //   27: invokevirtual 56	android/os/Parcel:writeStrongBinder	(Landroid/os/IBinder;)V
        //   30: aload_0
        //   31: getfield 17	com/google/android/gms/cast/framework/ab$a$a:a	Landroid/os/IBinder;
        //   34: iconst_2
        //   35: aload_2
        //   36: aload_3
        //   37: iconst_0
        //   38: invokeinterface 37 5 0
        //   43: pop
        //   44: aload_3
        //   45: invokevirtual 40	android/os/Parcel:readException	()V
        //   48: aload_3
        //   49: invokevirtual 46	android/os/Parcel:recycle	()V
        //   52: aload_2
        //   53: invokevirtual 46	android/os/Parcel:recycle	()V
        //   56: return
        //   57: aconst_null
        //   58: astore_1
        //   59: goto -34 -> 25
        //   62: astore_1
        //   63: aload_3
        //   64: invokevirtual 46	android/os/Parcel:recycle	()V
        //   67: aload_2
        //   68: invokevirtual 46	android/os/Parcel:recycle	()V
        //   71: aload_1
        //   72: athrow
        // Local variable table:
        //   start	length	slot	name	signature
        //   0	73	0	this	a
        //   0	73	1	parame	e
        //   3	65	2	localParcel1	Parcel
        //   7	57	3	localParcel2	Parcel
        // Exception table:
        //   from	to	target	type
        //   8	14	62	finally
        //   18	25	62	finally
        //   25	48	62	finally
      }
      
      /* Error */
      public void a(e parame, int paramInt)
      {
        // Byte code:
        //   0: invokestatic 25	android/os/Parcel:obtain	()Landroid/os/Parcel;
        //   3: astore_3
        //   4: invokestatic 25	android/os/Parcel:obtain	()Landroid/os/Parcel;
        //   7: astore 4
        //   9: aload_3
        //   10: ldc 27
        //   12: invokevirtual 31	android/os/Parcel:writeInterfaceToken	(Ljava/lang/String;)V
        //   15: aload_1
        //   16: ifnull +50 -> 66
        //   19: aload_1
        //   20: invokeinterface 53 1 0
        //   25: astore_1
        //   26: aload_3
        //   27: aload_1
        //   28: invokevirtual 56	android/os/Parcel:writeStrongBinder	(Landroid/os/IBinder;)V
        //   31: aload_3
        //   32: iload_2
        //   33: invokevirtual 61	android/os/Parcel:writeInt	(I)V
        //   36: aload_0
        //   37: getfield 17	com/google/android/gms/cast/framework/ab$a$a:a	Landroid/os/IBinder;
        //   40: iconst_4
        //   41: aload_3
        //   42: aload 4
        //   44: iconst_0
        //   45: invokeinterface 37 5 0
        //   50: pop
        //   51: aload 4
        //   53: invokevirtual 40	android/os/Parcel:readException	()V
        //   56: aload 4
        //   58: invokevirtual 46	android/os/Parcel:recycle	()V
        //   61: aload_3
        //   62: invokevirtual 46	android/os/Parcel:recycle	()V
        //   65: return
        //   66: aconst_null
        //   67: astore_1
        //   68: goto -42 -> 26
        //   71: astore_1
        //   72: aload 4
        //   74: invokevirtual 46	android/os/Parcel:recycle	()V
        //   77: aload_3
        //   78: invokevirtual 46	android/os/Parcel:recycle	()V
        //   81: aload_1
        //   82: athrow
        // Local variable table:
        //   start	length	slot	name	signature
        //   0	83	0	this	a
        //   0	83	1	parame	e
        //   0	83	2	paramInt	int
        //   3	75	3	localParcel1	Parcel
        //   7	66	4	localParcel2	Parcel
        // Exception table:
        //   from	to	target	type
        //   9	15	71	finally
        //   19	26	71	finally
        //   26	56	71	finally
      }
      
      /* Error */
      public void a(e parame, String paramString)
      {
        // Byte code:
        //   0: invokestatic 25	android/os/Parcel:obtain	()Landroid/os/Parcel;
        //   3: astore_3
        //   4: invokestatic 25	android/os/Parcel:obtain	()Landroid/os/Parcel;
        //   7: astore 4
        //   9: aload_3
        //   10: ldc 27
        //   12: invokevirtual 31	android/os/Parcel:writeInterfaceToken	(Ljava/lang/String;)V
        //   15: aload_1
        //   16: ifnull +50 -> 66
        //   19: aload_1
        //   20: invokeinterface 53 1 0
        //   25: astore_1
        //   26: aload_3
        //   27: aload_1
        //   28: invokevirtual 56	android/os/Parcel:writeStrongBinder	(Landroid/os/IBinder;)V
        //   31: aload_3
        //   32: aload_2
        //   33: invokevirtual 65	android/os/Parcel:writeString	(Ljava/lang/String;)V
        //   36: aload_0
        //   37: getfield 17	com/google/android/gms/cast/framework/ab$a$a:a	Landroid/os/IBinder;
        //   40: iconst_3
        //   41: aload_3
        //   42: aload 4
        //   44: iconst_0
        //   45: invokeinterface 37 5 0
        //   50: pop
        //   51: aload 4
        //   53: invokevirtual 40	android/os/Parcel:readException	()V
        //   56: aload 4
        //   58: invokevirtual 46	android/os/Parcel:recycle	()V
        //   61: aload_3
        //   62: invokevirtual 46	android/os/Parcel:recycle	()V
        //   65: return
        //   66: aconst_null
        //   67: astore_1
        //   68: goto -42 -> 26
        //   71: astore_1
        //   72: aload 4
        //   74: invokevirtual 46	android/os/Parcel:recycle	()V
        //   77: aload_3
        //   78: invokevirtual 46	android/os/Parcel:recycle	()V
        //   81: aload_1
        //   82: athrow
        // Local variable table:
        //   start	length	slot	name	signature
        //   0	83	0	this	a
        //   0	83	1	parame	e
        //   0	83	2	paramString	String
        //   3	75	3	localParcel1	Parcel
        //   7	66	4	localParcel2	Parcel
        // Exception table:
        //   from	to	target	type
        //   9	15	71	finally
        //   19	26	71	finally
        //   26	56	71	finally
      }
      
      /* Error */
      public void a(e parame, boolean paramBoolean)
      {
        // Byte code:
        //   0: iconst_0
        //   1: istore_3
        //   2: invokestatic 25	android/os/Parcel:obtain	()Landroid/os/Parcel;
        //   5: astore 4
        //   7: invokestatic 25	android/os/Parcel:obtain	()Landroid/os/Parcel;
        //   10: astore 5
        //   12: aload 4
        //   14: ldc 27
        //   16: invokevirtual 31	android/os/Parcel:writeInterfaceToken	(Ljava/lang/String;)V
        //   19: aload_1
        //   20: ifnull +61 -> 81
        //   23: aload_1
        //   24: invokeinterface 53 1 0
        //   29: astore_1
        //   30: aload 4
        //   32: aload_1
        //   33: invokevirtual 56	android/os/Parcel:writeStrongBinder	(Landroid/os/IBinder;)V
        //   36: iload_2
        //   37: ifeq +5 -> 42
        //   40: iconst_1
        //   41: istore_3
        //   42: aload 4
        //   44: iload_3
        //   45: invokevirtual 61	android/os/Parcel:writeInt	(I)V
        //   48: aload_0
        //   49: getfield 17	com/google/android/gms/cast/framework/ab$a$a:a	Landroid/os/IBinder;
        //   52: bipush 8
        //   54: aload 4
        //   56: aload 5
        //   58: iconst_0
        //   59: invokeinterface 37 5 0
        //   64: pop
        //   65: aload 5
        //   67: invokevirtual 40	android/os/Parcel:readException	()V
        //   70: aload 5
        //   72: invokevirtual 46	android/os/Parcel:recycle	()V
        //   75: aload 4
        //   77: invokevirtual 46	android/os/Parcel:recycle	()V
        //   80: return
        //   81: aconst_null
        //   82: astore_1
        //   83: goto -53 -> 30
        //   86: astore_1
        //   87: aload 5
        //   89: invokevirtual 46	android/os/Parcel:recycle	()V
        //   92: aload 4
        //   94: invokevirtual 46	android/os/Parcel:recycle	()V
        //   97: aload_1
        //   98: athrow
        // Local variable table:
        //   start	length	slot	name	signature
        //   0	99	0	this	a
        //   0	99	1	parame	e
        //   0	99	2	paramBoolean	boolean
        //   1	44	3	i	int
        //   5	88	4	localParcel1	Parcel
        //   10	78	5	localParcel2	Parcel
        // Exception table:
        //   from	to	target	type
        //   12	19	86	finally
        //   23	30	86	finally
        //   30	36	86	finally
        //   42	70	86	finally
      }
      
      public IBinder asBinder()
      {
        return this.a;
      }
      
      public e b()
      {
        Parcel localParcel1 = Parcel.obtain();
        Parcel localParcel2 = Parcel.obtain();
        try
        {
          localParcel1.writeInterfaceToken("com.google.android.gms.cast.framework.ISessionManagerListener");
          this.a.transact(1, localParcel1, localParcel2, 0);
          localParcel2.readException();
          e locale = e.a.a(localParcel2.readStrongBinder());
          return locale;
        }
        finally
        {
          localParcel2.recycle();
          localParcel1.recycle();
        }
      }
      
      /* Error */
      public void b(e parame)
      {
        // Byte code:
        //   0: invokestatic 25	android/os/Parcel:obtain	()Landroid/os/Parcel;
        //   3: astore_2
        //   4: invokestatic 25	android/os/Parcel:obtain	()Landroid/os/Parcel;
        //   7: astore_3
        //   8: aload_2
        //   9: ldc 27
        //   11: invokevirtual 31	android/os/Parcel:writeInterfaceToken	(Ljava/lang/String;)V
        //   14: aload_1
        //   15: ifnull +42 -> 57
        //   18: aload_1
        //   19: invokeinterface 53 1 0
        //   24: astore_1
        //   25: aload_2
        //   26: aload_1
        //   27: invokevirtual 56	android/os/Parcel:writeStrongBinder	(Landroid/os/IBinder;)V
        //   30: aload_0
        //   31: getfield 17	com/google/android/gms/cast/framework/ab$a$a:a	Landroid/os/IBinder;
        //   34: iconst_5
        //   35: aload_2
        //   36: aload_3
        //   37: iconst_0
        //   38: invokeinterface 37 5 0
        //   43: pop
        //   44: aload_3
        //   45: invokevirtual 40	android/os/Parcel:readException	()V
        //   48: aload_3
        //   49: invokevirtual 46	android/os/Parcel:recycle	()V
        //   52: aload_2
        //   53: invokevirtual 46	android/os/Parcel:recycle	()V
        //   56: return
        //   57: aconst_null
        //   58: astore_1
        //   59: goto -34 -> 25
        //   62: astore_1
        //   63: aload_3
        //   64: invokevirtual 46	android/os/Parcel:recycle	()V
        //   67: aload_2
        //   68: invokevirtual 46	android/os/Parcel:recycle	()V
        //   71: aload_1
        //   72: athrow
        // Local variable table:
        //   start	length	slot	name	signature
        //   0	73	0	this	a
        //   0	73	1	parame	e
        //   3	65	2	localParcel1	Parcel
        //   7	57	3	localParcel2	Parcel
        // Exception table:
        //   from	to	target	type
        //   8	14	62	finally
        //   18	25	62	finally
        //   25	48	62	finally
      }
      
      /* Error */
      public void b(e parame, int paramInt)
      {
        // Byte code:
        //   0: invokestatic 25	android/os/Parcel:obtain	()Landroid/os/Parcel;
        //   3: astore_3
        //   4: invokestatic 25	android/os/Parcel:obtain	()Landroid/os/Parcel;
        //   7: astore 4
        //   9: aload_3
        //   10: ldc 27
        //   12: invokevirtual 31	android/os/Parcel:writeInterfaceToken	(Ljava/lang/String;)V
        //   15: aload_1
        //   16: ifnull +51 -> 67
        //   19: aload_1
        //   20: invokeinterface 53 1 0
        //   25: astore_1
        //   26: aload_3
        //   27: aload_1
        //   28: invokevirtual 56	android/os/Parcel:writeStrongBinder	(Landroid/os/IBinder;)V
        //   31: aload_3
        //   32: iload_2
        //   33: invokevirtual 61	android/os/Parcel:writeInt	(I)V
        //   36: aload_0
        //   37: getfield 17	com/google/android/gms/cast/framework/ab$a$a:a	Landroid/os/IBinder;
        //   40: bipush 6
        //   42: aload_3
        //   43: aload 4
        //   45: iconst_0
        //   46: invokeinterface 37 5 0
        //   51: pop
        //   52: aload 4
        //   54: invokevirtual 40	android/os/Parcel:readException	()V
        //   57: aload 4
        //   59: invokevirtual 46	android/os/Parcel:recycle	()V
        //   62: aload_3
        //   63: invokevirtual 46	android/os/Parcel:recycle	()V
        //   66: return
        //   67: aconst_null
        //   68: astore_1
        //   69: goto -43 -> 26
        //   72: astore_1
        //   73: aload 4
        //   75: invokevirtual 46	android/os/Parcel:recycle	()V
        //   78: aload_3
        //   79: invokevirtual 46	android/os/Parcel:recycle	()V
        //   82: aload_1
        //   83: athrow
        // Local variable table:
        //   start	length	slot	name	signature
        //   0	84	0	this	a
        //   0	84	1	parame	e
        //   0	84	2	paramInt	int
        //   3	76	3	localParcel1	Parcel
        //   7	67	4	localParcel2	Parcel
        // Exception table:
        //   from	to	target	type
        //   9	15	72	finally
        //   19	26	72	finally
        //   26	57	72	finally
      }
      
      /* Error */
      public void b(e parame, String paramString)
      {
        // Byte code:
        //   0: invokestatic 25	android/os/Parcel:obtain	()Landroid/os/Parcel;
        //   3: astore_3
        //   4: invokestatic 25	android/os/Parcel:obtain	()Landroid/os/Parcel;
        //   7: astore 4
        //   9: aload_3
        //   10: ldc 27
        //   12: invokevirtual 31	android/os/Parcel:writeInterfaceToken	(Ljava/lang/String;)V
        //   15: aload_1
        //   16: ifnull +51 -> 67
        //   19: aload_1
        //   20: invokeinterface 53 1 0
        //   25: astore_1
        //   26: aload_3
        //   27: aload_1
        //   28: invokevirtual 56	android/os/Parcel:writeStrongBinder	(Landroid/os/IBinder;)V
        //   31: aload_3
        //   32: aload_2
        //   33: invokevirtual 65	android/os/Parcel:writeString	(Ljava/lang/String;)V
        //   36: aload_0
        //   37: getfield 17	com/google/android/gms/cast/framework/ab$a$a:a	Landroid/os/IBinder;
        //   40: bipush 7
        //   42: aload_3
        //   43: aload 4
        //   45: iconst_0
        //   46: invokeinterface 37 5 0
        //   51: pop
        //   52: aload 4
        //   54: invokevirtual 40	android/os/Parcel:readException	()V
        //   57: aload 4
        //   59: invokevirtual 46	android/os/Parcel:recycle	()V
        //   62: aload_3
        //   63: invokevirtual 46	android/os/Parcel:recycle	()V
        //   66: return
        //   67: aconst_null
        //   68: astore_1
        //   69: goto -43 -> 26
        //   72: astore_1
        //   73: aload 4
        //   75: invokevirtual 46	android/os/Parcel:recycle	()V
        //   78: aload_3
        //   79: invokevirtual 46	android/os/Parcel:recycle	()V
        //   82: aload_1
        //   83: athrow
        // Local variable table:
        //   start	length	slot	name	signature
        //   0	84	0	this	a
        //   0	84	1	parame	e
        //   0	84	2	paramString	String
        //   3	76	3	localParcel1	Parcel
        //   7	67	4	localParcel2	Parcel
        // Exception table:
        //   from	to	target	type
        //   9	15	72	finally
        //   19	26	72	finally
        //   26	57	72	finally
      }
      
      /* Error */
      public void c(e parame, int paramInt)
      {
        // Byte code:
        //   0: invokestatic 25	android/os/Parcel:obtain	()Landroid/os/Parcel;
        //   3: astore_3
        //   4: invokestatic 25	android/os/Parcel:obtain	()Landroid/os/Parcel;
        //   7: astore 4
        //   9: aload_3
        //   10: ldc 27
        //   12: invokevirtual 31	android/os/Parcel:writeInterfaceToken	(Ljava/lang/String;)V
        //   15: aload_1
        //   16: ifnull +51 -> 67
        //   19: aload_1
        //   20: invokeinterface 53 1 0
        //   25: astore_1
        //   26: aload_3
        //   27: aload_1
        //   28: invokevirtual 56	android/os/Parcel:writeStrongBinder	(Landroid/os/IBinder;)V
        //   31: aload_3
        //   32: iload_2
        //   33: invokevirtual 61	android/os/Parcel:writeInt	(I)V
        //   36: aload_0
        //   37: getfield 17	com/google/android/gms/cast/framework/ab$a$a:a	Landroid/os/IBinder;
        //   40: bipush 9
        //   42: aload_3
        //   43: aload 4
        //   45: iconst_0
        //   46: invokeinterface 37 5 0
        //   51: pop
        //   52: aload 4
        //   54: invokevirtual 40	android/os/Parcel:readException	()V
        //   57: aload 4
        //   59: invokevirtual 46	android/os/Parcel:recycle	()V
        //   62: aload_3
        //   63: invokevirtual 46	android/os/Parcel:recycle	()V
        //   66: return
        //   67: aconst_null
        //   68: astore_1
        //   69: goto -43 -> 26
        //   72: astore_1
        //   73: aload 4
        //   75: invokevirtual 46	android/os/Parcel:recycle	()V
        //   78: aload_3
        //   79: invokevirtual 46	android/os/Parcel:recycle	()V
        //   82: aload_1
        //   83: athrow
        // Local variable table:
        //   start	length	slot	name	signature
        //   0	84	0	this	a
        //   0	84	1	parame	e
        //   0	84	2	paramInt	int
        //   3	76	3	localParcel1	Parcel
        //   7	67	4	localParcel2	Parcel
        // Exception table:
        //   from	to	target	type
        //   9	15	72	finally
        //   19	26	72	finally
        //   26	57	72	finally
      }
      
      /* Error */
      public void d(e parame, int paramInt)
      {
        // Byte code:
        //   0: invokestatic 25	android/os/Parcel:obtain	()Landroid/os/Parcel;
        //   3: astore_3
        //   4: invokestatic 25	android/os/Parcel:obtain	()Landroid/os/Parcel;
        //   7: astore 4
        //   9: aload_3
        //   10: ldc 27
        //   12: invokevirtual 31	android/os/Parcel:writeInterfaceToken	(Ljava/lang/String;)V
        //   15: aload_1
        //   16: ifnull +51 -> 67
        //   19: aload_1
        //   20: invokeinterface 53 1 0
        //   25: astore_1
        //   26: aload_3
        //   27: aload_1
        //   28: invokevirtual 56	android/os/Parcel:writeStrongBinder	(Landroid/os/IBinder;)V
        //   31: aload_3
        //   32: iload_2
        //   33: invokevirtual 61	android/os/Parcel:writeInt	(I)V
        //   36: aload_0
        //   37: getfield 17	com/google/android/gms/cast/framework/ab$a$a:a	Landroid/os/IBinder;
        //   40: bipush 10
        //   42: aload_3
        //   43: aload 4
        //   45: iconst_0
        //   46: invokeinterface 37 5 0
        //   51: pop
        //   52: aload 4
        //   54: invokevirtual 40	android/os/Parcel:readException	()V
        //   57: aload 4
        //   59: invokevirtual 46	android/os/Parcel:recycle	()V
        //   62: aload_3
        //   63: invokevirtual 46	android/os/Parcel:recycle	()V
        //   66: return
        //   67: aconst_null
        //   68: astore_1
        //   69: goto -43 -> 26
        //   72: astore_1
        //   73: aload 4
        //   75: invokevirtual 46	android/os/Parcel:recycle	()V
        //   78: aload_3
        //   79: invokevirtual 46	android/os/Parcel:recycle	()V
        //   82: aload_1
        //   83: athrow
        // Local variable table:
        //   start	length	slot	name	signature
        //   0	84	0	this	a
        //   0	84	1	parame	e
        //   0	84	2	paramInt	int
        //   3	76	3	localParcel1	Parcel
        //   7	67	4	localParcel2	Parcel
        // Exception table:
        //   from	to	target	type
        //   9	15	72	finally
        //   19	26	72	finally
        //   26	57	72	finally
      }
    }
  }
}


/* Location:              /Users/andi/Downloads/dex2jar-2.0/classes-dex2jar.jar!/com/google/android/gms/cast/framework/ab.class
 * Java compiler version: 6 (50.0)
 * JD-Core Version:       0.7.1
 */