package com.google.android.gms.cast.framework;

import android.os.Binder;
import android.os.Bundle;
import android.os.IBinder;
import android.os.IInterface;
import android.os.Parcel;
import com.google.android.gms.c.e;
import com.google.android.gms.c.e.a;

public abstract interface t
  extends IInterface
{
  public abstract Bundle a();
  
  public abstract void a(e parame);
  
  public abstract void a(r paramr);
  
  public abstract void b(e parame);
  
  public abstract void b(r paramr);
  
  public abstract boolean b();
  
  public abstract aa c();
  
  public abstract w d();
  
  public abstract void e();
  
  public abstract e f();
  
  public static abstract class a
    extends Binder
    implements t
  {
    public static t a(IBinder paramIBinder)
    {
      if (paramIBinder == null) {
        return null;
      }
      IInterface localIInterface = paramIBinder.queryLocalInterface("com.google.android.gms.cast.framework.ICastContext");
      if ((localIInterface != null) && ((localIInterface instanceof t))) {
        return (t)localIInterface;
      }
      return new a(paramIBinder);
    }
    
    public boolean onTransact(int paramInt1, Parcel paramParcel1, Parcel paramParcel2, int paramInt2)
    {
      int i = 0;
      w localw = null;
      e locale = null;
      switch (paramInt1)
      {
      default: 
        return super.onTransact(paramInt1, paramParcel1, paramParcel2, paramInt2);
      case 1598968902: 
        paramParcel2.writeString("com.google.android.gms.cast.framework.ICastContext");
        return true;
      case 1: 
        paramParcel1.enforceInterface("com.google.android.gms.cast.framework.ICastContext");
        paramParcel1 = a();
        paramParcel2.writeNoException();
        if (paramParcel1 != null)
        {
          paramParcel2.writeInt(1);
          paramParcel1.writeToParcel(paramParcel2, 1);
          return true;
        }
        paramParcel2.writeInt(0);
        return true;
      case 2: 
        paramParcel1.enforceInterface("com.google.android.gms.cast.framework.ICastContext");
        boolean bool = b();
        paramParcel2.writeNoException();
        paramInt1 = i;
        if (bool) {
          paramInt1 = 1;
        }
        paramParcel2.writeInt(paramInt1);
        return true;
      case 3: 
        paramParcel1.enforceInterface("com.google.android.gms.cast.framework.ICastContext");
        a(r.a.a(paramParcel1.readStrongBinder()));
        paramParcel2.writeNoException();
        return true;
      case 4: 
        paramParcel1.enforceInterface("com.google.android.gms.cast.framework.ICastContext");
        b(r.a.a(paramParcel1.readStrongBinder()));
        paramParcel2.writeNoException();
        return true;
      case 5: 
        paramParcel1.enforceInterface("com.google.android.gms.cast.framework.ICastContext");
        paramParcel1 = c();
        paramParcel2.writeNoException();
        if (paramParcel1 != null) {}
        for (paramParcel1 = paramParcel1.asBinder();; paramParcel1 = null)
        {
          paramParcel2.writeStrongBinder(paramParcel1);
          return true;
        }
      case 6: 
        paramParcel1.enforceInterface("com.google.android.gms.cast.framework.ICastContext");
        localw = d();
        paramParcel2.writeNoException();
        paramParcel1 = locale;
        if (localw != null) {
          paramParcel1 = localw.asBinder();
        }
        paramParcel2.writeStrongBinder(paramParcel1);
        return true;
      case 7: 
        paramParcel1.enforceInterface("com.google.android.gms.cast.framework.ICastContext");
        e();
        paramParcel2.writeNoException();
        return true;
      case 8: 
        paramParcel1.enforceInterface("com.google.android.gms.cast.framework.ICastContext");
        a(e.a.a(paramParcel1.readStrongBinder()));
        paramParcel2.writeNoException();
        return true;
      case 9: 
        paramParcel1.enforceInterface("com.google.android.gms.cast.framework.ICastContext");
        b(e.a.a(paramParcel1.readStrongBinder()));
        paramParcel2.writeNoException();
        return true;
      }
      paramParcel1.enforceInterface("com.google.android.gms.cast.framework.ICastContext");
      locale = f();
      paramParcel2.writeNoException();
      paramParcel1 = localw;
      if (locale != null) {
        paramParcel1 = locale.asBinder();
      }
      paramParcel2.writeStrongBinder(paramParcel1);
      return true;
    }
    
    private static class a
      implements t
    {
      private IBinder a;
      
      a(IBinder paramIBinder)
      {
        this.a = paramIBinder;
      }
      
      /* Error */
      public Bundle a()
      {
        // Byte code:
        //   0: invokestatic 25	android/os/Parcel:obtain	()Landroid/os/Parcel;
        //   3: astore_2
        //   4: invokestatic 25	android/os/Parcel:obtain	()Landroid/os/Parcel;
        //   7: astore_3
        //   8: aload_2
        //   9: ldc 27
        //   11: invokevirtual 31	android/os/Parcel:writeInterfaceToken	(Ljava/lang/String;)V
        //   14: aload_0
        //   15: getfield 17	com/google/android/gms/cast/framework/t$a$a:a	Landroid/os/IBinder;
        //   18: iconst_1
        //   19: aload_2
        //   20: aload_3
        //   21: iconst_0
        //   22: invokeinterface 37 5 0
        //   27: pop
        //   28: aload_3
        //   29: invokevirtual 40	android/os/Parcel:readException	()V
        //   32: aload_3
        //   33: invokevirtual 44	android/os/Parcel:readInt	()I
        //   36: ifeq +26 -> 62
        //   39: getstatic 50	android/os/Bundle:CREATOR	Landroid/os/Parcelable$Creator;
        //   42: aload_3
        //   43: invokeinterface 56 2 0
        //   48: checkcast 46	android/os/Bundle
        //   51: astore_1
        //   52: aload_3
        //   53: invokevirtual 59	android/os/Parcel:recycle	()V
        //   56: aload_2
        //   57: invokevirtual 59	android/os/Parcel:recycle	()V
        //   60: aload_1
        //   61: areturn
        //   62: aconst_null
        //   63: astore_1
        //   64: goto -12 -> 52
        //   67: astore_1
        //   68: aload_3
        //   69: invokevirtual 59	android/os/Parcel:recycle	()V
        //   72: aload_2
        //   73: invokevirtual 59	android/os/Parcel:recycle	()V
        //   76: aload_1
        //   77: athrow
        // Local variable table:
        //   start	length	slot	name	signature
        //   0	78	0	this	a
        //   51	13	1	localBundle	Bundle
        //   67	10	1	localObject	Object
        //   3	70	2	localParcel1	Parcel
        //   7	62	3	localParcel2	Parcel
        // Exception table:
        //   from	to	target	type
        //   8	52	67	finally
      }
      
      /* Error */
      public void a(e parame)
      {
        // Byte code:
        //   0: invokestatic 25	android/os/Parcel:obtain	()Landroid/os/Parcel;
        //   3: astore_2
        //   4: invokestatic 25	android/os/Parcel:obtain	()Landroid/os/Parcel;
        //   7: astore_3
        //   8: aload_2
        //   9: ldc 27
        //   11: invokevirtual 31	android/os/Parcel:writeInterfaceToken	(Ljava/lang/String;)V
        //   14: aload_1
        //   15: ifnull +43 -> 58
        //   18: aload_1
        //   19: invokeinterface 66 1 0
        //   24: astore_1
        //   25: aload_2
        //   26: aload_1
        //   27: invokevirtual 69	android/os/Parcel:writeStrongBinder	(Landroid/os/IBinder;)V
        //   30: aload_0
        //   31: getfield 17	com/google/android/gms/cast/framework/t$a$a:a	Landroid/os/IBinder;
        //   34: bipush 8
        //   36: aload_2
        //   37: aload_3
        //   38: iconst_0
        //   39: invokeinterface 37 5 0
        //   44: pop
        //   45: aload_3
        //   46: invokevirtual 40	android/os/Parcel:readException	()V
        //   49: aload_3
        //   50: invokevirtual 59	android/os/Parcel:recycle	()V
        //   53: aload_2
        //   54: invokevirtual 59	android/os/Parcel:recycle	()V
        //   57: return
        //   58: aconst_null
        //   59: astore_1
        //   60: goto -35 -> 25
        //   63: astore_1
        //   64: aload_3
        //   65: invokevirtual 59	android/os/Parcel:recycle	()V
        //   68: aload_2
        //   69: invokevirtual 59	android/os/Parcel:recycle	()V
        //   72: aload_1
        //   73: athrow
        // Local variable table:
        //   start	length	slot	name	signature
        //   0	74	0	this	a
        //   0	74	1	parame	e
        //   3	66	2	localParcel1	Parcel
        //   7	58	3	localParcel2	Parcel
        // Exception table:
        //   from	to	target	type
        //   8	14	63	finally
        //   18	25	63	finally
        //   25	49	63	finally
      }
      
      /* Error */
      public void a(r paramr)
      {
        // Byte code:
        //   0: invokestatic 25	android/os/Parcel:obtain	()Landroid/os/Parcel;
        //   3: astore_2
        //   4: invokestatic 25	android/os/Parcel:obtain	()Landroid/os/Parcel;
        //   7: astore_3
        //   8: aload_2
        //   9: ldc 27
        //   11: invokevirtual 31	android/os/Parcel:writeInterfaceToken	(Ljava/lang/String;)V
        //   14: aload_1
        //   15: ifnull +42 -> 57
        //   18: aload_1
        //   19: invokeinterface 73 1 0
        //   24: astore_1
        //   25: aload_2
        //   26: aload_1
        //   27: invokevirtual 69	android/os/Parcel:writeStrongBinder	(Landroid/os/IBinder;)V
        //   30: aload_0
        //   31: getfield 17	com/google/android/gms/cast/framework/t$a$a:a	Landroid/os/IBinder;
        //   34: iconst_3
        //   35: aload_2
        //   36: aload_3
        //   37: iconst_0
        //   38: invokeinterface 37 5 0
        //   43: pop
        //   44: aload_3
        //   45: invokevirtual 40	android/os/Parcel:readException	()V
        //   48: aload_3
        //   49: invokevirtual 59	android/os/Parcel:recycle	()V
        //   52: aload_2
        //   53: invokevirtual 59	android/os/Parcel:recycle	()V
        //   56: return
        //   57: aconst_null
        //   58: astore_1
        //   59: goto -34 -> 25
        //   62: astore_1
        //   63: aload_3
        //   64: invokevirtual 59	android/os/Parcel:recycle	()V
        //   67: aload_2
        //   68: invokevirtual 59	android/os/Parcel:recycle	()V
        //   71: aload_1
        //   72: athrow
        // Local variable table:
        //   start	length	slot	name	signature
        //   0	73	0	this	a
        //   0	73	1	paramr	r
        //   3	65	2	localParcel1	Parcel
        //   7	57	3	localParcel2	Parcel
        // Exception table:
        //   from	to	target	type
        //   8	14	62	finally
        //   18	25	62	finally
        //   25	48	62	finally
      }
      
      public IBinder asBinder()
      {
        return this.a;
      }
      
      /* Error */
      public void b(e parame)
      {
        // Byte code:
        //   0: invokestatic 25	android/os/Parcel:obtain	()Landroid/os/Parcel;
        //   3: astore_2
        //   4: invokestatic 25	android/os/Parcel:obtain	()Landroid/os/Parcel;
        //   7: astore_3
        //   8: aload_2
        //   9: ldc 27
        //   11: invokevirtual 31	android/os/Parcel:writeInterfaceToken	(Ljava/lang/String;)V
        //   14: aload_1
        //   15: ifnull +43 -> 58
        //   18: aload_1
        //   19: invokeinterface 66 1 0
        //   24: astore_1
        //   25: aload_2
        //   26: aload_1
        //   27: invokevirtual 69	android/os/Parcel:writeStrongBinder	(Landroid/os/IBinder;)V
        //   30: aload_0
        //   31: getfield 17	com/google/android/gms/cast/framework/t$a$a:a	Landroid/os/IBinder;
        //   34: bipush 9
        //   36: aload_2
        //   37: aload_3
        //   38: iconst_0
        //   39: invokeinterface 37 5 0
        //   44: pop
        //   45: aload_3
        //   46: invokevirtual 40	android/os/Parcel:readException	()V
        //   49: aload_3
        //   50: invokevirtual 59	android/os/Parcel:recycle	()V
        //   53: aload_2
        //   54: invokevirtual 59	android/os/Parcel:recycle	()V
        //   57: return
        //   58: aconst_null
        //   59: astore_1
        //   60: goto -35 -> 25
        //   63: astore_1
        //   64: aload_3
        //   65: invokevirtual 59	android/os/Parcel:recycle	()V
        //   68: aload_2
        //   69: invokevirtual 59	android/os/Parcel:recycle	()V
        //   72: aload_1
        //   73: athrow
        // Local variable table:
        //   start	length	slot	name	signature
        //   0	74	0	this	a
        //   0	74	1	parame	e
        //   3	66	2	localParcel1	Parcel
        //   7	58	3	localParcel2	Parcel
        // Exception table:
        //   from	to	target	type
        //   8	14	63	finally
        //   18	25	63	finally
        //   25	49	63	finally
      }
      
      /* Error */
      public void b(r paramr)
      {
        // Byte code:
        //   0: invokestatic 25	android/os/Parcel:obtain	()Landroid/os/Parcel;
        //   3: astore_2
        //   4: invokestatic 25	android/os/Parcel:obtain	()Landroid/os/Parcel;
        //   7: astore_3
        //   8: aload_2
        //   9: ldc 27
        //   11: invokevirtual 31	android/os/Parcel:writeInterfaceToken	(Ljava/lang/String;)V
        //   14: aload_1
        //   15: ifnull +42 -> 57
        //   18: aload_1
        //   19: invokeinterface 73 1 0
        //   24: astore_1
        //   25: aload_2
        //   26: aload_1
        //   27: invokevirtual 69	android/os/Parcel:writeStrongBinder	(Landroid/os/IBinder;)V
        //   30: aload_0
        //   31: getfield 17	com/google/android/gms/cast/framework/t$a$a:a	Landroid/os/IBinder;
        //   34: iconst_4
        //   35: aload_2
        //   36: aload_3
        //   37: iconst_0
        //   38: invokeinterface 37 5 0
        //   43: pop
        //   44: aload_3
        //   45: invokevirtual 40	android/os/Parcel:readException	()V
        //   48: aload_3
        //   49: invokevirtual 59	android/os/Parcel:recycle	()V
        //   52: aload_2
        //   53: invokevirtual 59	android/os/Parcel:recycle	()V
        //   56: return
        //   57: aconst_null
        //   58: astore_1
        //   59: goto -34 -> 25
        //   62: astore_1
        //   63: aload_3
        //   64: invokevirtual 59	android/os/Parcel:recycle	()V
        //   67: aload_2
        //   68: invokevirtual 59	android/os/Parcel:recycle	()V
        //   71: aload_1
        //   72: athrow
        // Local variable table:
        //   start	length	slot	name	signature
        //   0	73	0	this	a
        //   0	73	1	paramr	r
        //   3	65	2	localParcel1	Parcel
        //   7	57	3	localParcel2	Parcel
        // Exception table:
        //   from	to	target	type
        //   8	14	62	finally
        //   18	25	62	finally
        //   25	48	62	finally
      }
      
      public boolean b()
      {
        boolean bool = false;
        Parcel localParcel1 = Parcel.obtain();
        Parcel localParcel2 = Parcel.obtain();
        try
        {
          localParcel1.writeInterfaceToken("com.google.android.gms.cast.framework.ICastContext");
          this.a.transact(2, localParcel1, localParcel2, 0);
          localParcel2.readException();
          int i = localParcel2.readInt();
          if (i != 0) {
            bool = true;
          }
          return bool;
        }
        finally
        {
          localParcel2.recycle();
          localParcel1.recycle();
        }
      }
      
      public aa c()
      {
        Parcel localParcel1 = Parcel.obtain();
        Parcel localParcel2 = Parcel.obtain();
        try
        {
          localParcel1.writeInterfaceToken("com.google.android.gms.cast.framework.ICastContext");
          this.a.transact(5, localParcel1, localParcel2, 0);
          localParcel2.readException();
          aa localaa = aa.a.a(localParcel2.readStrongBinder());
          return localaa;
        }
        finally
        {
          localParcel2.recycle();
          localParcel1.recycle();
        }
      }
      
      public w d()
      {
        Parcel localParcel1 = Parcel.obtain();
        Parcel localParcel2 = Parcel.obtain();
        try
        {
          localParcel1.writeInterfaceToken("com.google.android.gms.cast.framework.ICastContext");
          this.a.transact(6, localParcel1, localParcel2, 0);
          localParcel2.readException();
          w localw = w.a.a(localParcel2.readStrongBinder());
          return localw;
        }
        finally
        {
          localParcel2.recycle();
          localParcel1.recycle();
        }
      }
      
      public void e()
      {
        Parcel localParcel1 = Parcel.obtain();
        Parcel localParcel2 = Parcel.obtain();
        try
        {
          localParcel1.writeInterfaceToken("com.google.android.gms.cast.framework.ICastContext");
          this.a.transact(7, localParcel1, localParcel2, 0);
          localParcel2.readException();
          return;
        }
        finally
        {
          localParcel2.recycle();
          localParcel1.recycle();
        }
      }
      
      public e f()
      {
        Parcel localParcel1 = Parcel.obtain();
        Parcel localParcel2 = Parcel.obtain();
        try
        {
          localParcel1.writeInterfaceToken("com.google.android.gms.cast.framework.ICastContext");
          this.a.transact(10, localParcel1, localParcel2, 0);
          localParcel2.readException();
          e locale = e.a.a(localParcel2.readStrongBinder());
          return locale;
        }
        finally
        {
          localParcel2.recycle();
          localParcel1.recycle();
        }
      }
    }
  }
}


/* Location:              /Users/andi/Downloads/dex2jar-2.0/classes-dex2jar.jar!/com/google/android/gms/cast/framework/t.class
 * Java compiler version: 6 (50.0)
 * JD-Core Version:       0.7.1
 */