package com.google.android.gms.cast.framework;

import android.os.Binder;
import android.os.Bundle;
import android.os.IBinder;
import android.os.IInterface;
import android.os.Parcel;
import android.os.Parcelable.Creator;
import com.google.android.gms.cast.ApplicationMetadata;
import com.google.android.gms.common.ConnectionResult;

public abstract interface u
  extends IInterface
{
  public abstract void a(int paramInt);
  
  public abstract void a(Bundle paramBundle);
  
  public abstract void a(ApplicationMetadata paramApplicationMetadata, String paramString1, String paramString2, boolean paramBoolean);
  
  public abstract void a(ConnectionResult paramConnectionResult);
  
  public abstract void a(boolean paramBoolean, int paramInt);
  
  public abstract void b(int paramInt);
  
  public static abstract class a
    extends Binder
    implements u
  {
    public static u a(IBinder paramIBinder)
    {
      if (paramIBinder == null) {
        return null;
      }
      IInterface localIInterface = paramIBinder.queryLocalInterface("com.google.android.gms.cast.framework.ICastSession");
      if ((localIInterface != null) && ((localIInterface instanceof u))) {
        return (u)localIInterface;
      }
      return new a(paramIBinder);
    }
    
    public boolean onTransact(int paramInt1, Parcel paramParcel1, Parcel paramParcel2, int paramInt2)
    {
      boolean bool2 = false;
      boolean bool1 = false;
      String str1 = null;
      String str2 = null;
      Object localObject = null;
      switch (paramInt1)
      {
      default: 
        return super.onTransact(paramInt1, paramParcel1, paramParcel2, paramInt2);
      case 1598968902: 
        paramParcel2.writeString("com.google.android.gms.cast.framework.ICastSession");
        return true;
      case 1: 
        paramParcel1.enforceInterface("com.google.android.gms.cast.framework.ICastSession");
        if (paramParcel1.readInt() != 0) {
          localObject = (Bundle)Bundle.CREATOR.createFromParcel(paramParcel1);
        }
        a((Bundle)localObject);
        paramParcel2.writeNoException();
        return true;
      case 2: 
        paramParcel1.enforceInterface("com.google.android.gms.cast.framework.ICastSession");
        a(paramParcel1.readInt());
        paramParcel2.writeNoException();
        return true;
      case 3: 
        paramParcel1.enforceInterface("com.google.android.gms.cast.framework.ICastSession");
        localObject = str1;
        if (paramParcel1.readInt() != 0) {
          localObject = (ConnectionResult)ConnectionResult.CREATOR.createFromParcel(paramParcel1);
        }
        a((ConnectionResult)localObject);
        paramParcel2.writeNoException();
        return true;
      case 4: 
        paramParcel1.enforceInterface("com.google.android.gms.cast.framework.ICastSession");
        localObject = str2;
        if (paramParcel1.readInt() != 0) {
          localObject = (ApplicationMetadata)ApplicationMetadata.CREATOR.createFromParcel(paramParcel1);
        }
        str1 = paramParcel1.readString();
        str2 = paramParcel1.readString();
        if (paramParcel1.readInt() != 0) {
          bool1 = true;
        }
        a((ApplicationMetadata)localObject, str1, str2, bool1);
        paramParcel2.writeNoException();
        return true;
      case 5: 
        paramParcel1.enforceInterface("com.google.android.gms.cast.framework.ICastSession");
        b(paramParcel1.readInt());
        paramParcel2.writeNoException();
        return true;
      }
      paramParcel1.enforceInterface("com.google.android.gms.cast.framework.ICastSession");
      bool1 = bool2;
      if (paramParcel1.readInt() != 0) {
        bool1 = true;
      }
      a(bool1, paramParcel1.readInt());
      paramParcel2.writeNoException();
      return true;
    }
    
    private static class a
      implements u
    {
      private IBinder a;
      
      a(IBinder paramIBinder)
      {
        this.a = paramIBinder;
      }
      
      public void a(int paramInt)
      {
        Parcel localParcel1 = Parcel.obtain();
        Parcel localParcel2 = Parcel.obtain();
        try
        {
          localParcel1.writeInterfaceToken("com.google.android.gms.cast.framework.ICastSession");
          localParcel1.writeInt(paramInt);
          this.a.transact(2, localParcel1, localParcel2, 0);
          localParcel2.readException();
          return;
        }
        finally
        {
          localParcel2.recycle();
          localParcel1.recycle();
        }
      }
      
      /* Error */
      public void a(Bundle paramBundle)
      {
        // Byte code:
        //   0: invokestatic 25	android/os/Parcel:obtain	()Landroid/os/Parcel;
        //   3: astore_2
        //   4: invokestatic 25	android/os/Parcel:obtain	()Landroid/os/Parcel;
        //   7: astore_3
        //   8: aload_2
        //   9: ldc 27
        //   11: invokevirtual 31	android/os/Parcel:writeInterfaceToken	(Ljava/lang/String;)V
        //   14: aload_1
        //   15: ifnull +41 -> 56
        //   18: aload_2
        //   19: iconst_1
        //   20: invokevirtual 34	android/os/Parcel:writeInt	(I)V
        //   23: aload_1
        //   24: aload_2
        //   25: iconst_0
        //   26: invokevirtual 53	android/os/Bundle:writeToParcel	(Landroid/os/Parcel;I)V
        //   29: aload_0
        //   30: getfield 17	com/google/android/gms/cast/framework/u$a$a:a	Landroid/os/IBinder;
        //   33: iconst_1
        //   34: aload_2
        //   35: aload_3
        //   36: iconst_0
        //   37: invokeinterface 40 5 0
        //   42: pop
        //   43: aload_3
        //   44: invokevirtual 43	android/os/Parcel:readException	()V
        //   47: aload_3
        //   48: invokevirtual 46	android/os/Parcel:recycle	()V
        //   51: aload_2
        //   52: invokevirtual 46	android/os/Parcel:recycle	()V
        //   55: return
        //   56: aload_2
        //   57: iconst_0
        //   58: invokevirtual 34	android/os/Parcel:writeInt	(I)V
        //   61: goto -32 -> 29
        //   64: astore_1
        //   65: aload_3
        //   66: invokevirtual 46	android/os/Parcel:recycle	()V
        //   69: aload_2
        //   70: invokevirtual 46	android/os/Parcel:recycle	()V
        //   73: aload_1
        //   74: athrow
        // Local variable table:
        //   start	length	slot	name	signature
        //   0	75	0	this	a
        //   0	75	1	paramBundle	Bundle
        //   3	67	2	localParcel1	Parcel
        //   7	59	3	localParcel2	Parcel
        // Exception table:
        //   from	to	target	type
        //   8	14	64	finally
        //   18	29	64	finally
        //   29	47	64	finally
        //   56	61	64	finally
      }
      
      public void a(ApplicationMetadata paramApplicationMetadata, String paramString1, String paramString2, boolean paramBoolean)
      {
        int i = 1;
        Parcel localParcel1 = Parcel.obtain();
        Parcel localParcel2 = Parcel.obtain();
        for (;;)
        {
          try
          {
            localParcel1.writeInterfaceToken("com.google.android.gms.cast.framework.ICastSession");
            if (paramApplicationMetadata != null)
            {
              localParcel1.writeInt(1);
              paramApplicationMetadata.writeToParcel(localParcel1, 0);
              localParcel1.writeString(paramString1);
              localParcel1.writeString(paramString2);
              if (paramBoolean)
              {
                localParcel1.writeInt(i);
                this.a.transact(4, localParcel1, localParcel2, 0);
                localParcel2.readException();
              }
            }
            else
            {
              localParcel1.writeInt(0);
              continue;
            }
            i = 0;
          }
          finally
          {
            localParcel2.recycle();
            localParcel1.recycle();
          }
        }
      }
      
      /* Error */
      public void a(ConnectionResult paramConnectionResult)
      {
        // Byte code:
        //   0: invokestatic 25	android/os/Parcel:obtain	()Landroid/os/Parcel;
        //   3: astore_2
        //   4: invokestatic 25	android/os/Parcel:obtain	()Landroid/os/Parcel;
        //   7: astore_3
        //   8: aload_2
        //   9: ldc 27
        //   11: invokevirtual 31	android/os/Parcel:writeInterfaceToken	(Ljava/lang/String;)V
        //   14: aload_1
        //   15: ifnull +41 -> 56
        //   18: aload_2
        //   19: iconst_1
        //   20: invokevirtual 34	android/os/Parcel:writeInt	(I)V
        //   23: aload_1
        //   24: aload_2
        //   25: iconst_0
        //   26: invokevirtual 64	com/google/android/gms/common/ConnectionResult:writeToParcel	(Landroid/os/Parcel;I)V
        //   29: aload_0
        //   30: getfield 17	com/google/android/gms/cast/framework/u$a$a:a	Landroid/os/IBinder;
        //   33: iconst_3
        //   34: aload_2
        //   35: aload_3
        //   36: iconst_0
        //   37: invokeinterface 40 5 0
        //   42: pop
        //   43: aload_3
        //   44: invokevirtual 43	android/os/Parcel:readException	()V
        //   47: aload_3
        //   48: invokevirtual 46	android/os/Parcel:recycle	()V
        //   51: aload_2
        //   52: invokevirtual 46	android/os/Parcel:recycle	()V
        //   55: return
        //   56: aload_2
        //   57: iconst_0
        //   58: invokevirtual 34	android/os/Parcel:writeInt	(I)V
        //   61: goto -32 -> 29
        //   64: astore_1
        //   65: aload_3
        //   66: invokevirtual 46	android/os/Parcel:recycle	()V
        //   69: aload_2
        //   70: invokevirtual 46	android/os/Parcel:recycle	()V
        //   73: aload_1
        //   74: athrow
        // Local variable table:
        //   start	length	slot	name	signature
        //   0	75	0	this	a
        //   0	75	1	paramConnectionResult	ConnectionResult
        //   3	67	2	localParcel1	Parcel
        //   7	59	3	localParcel2	Parcel
        // Exception table:
        //   from	to	target	type
        //   8	14	64	finally
        //   18	29	64	finally
        //   29	47	64	finally
        //   56	61	64	finally
      }
      
      public void a(boolean paramBoolean, int paramInt)
      {
        int i = 0;
        Parcel localParcel1 = Parcel.obtain();
        Parcel localParcel2 = Parcel.obtain();
        try
        {
          localParcel1.writeInterfaceToken("com.google.android.gms.cast.framework.ICastSession");
          if (paramBoolean) {
            i = 1;
          }
          localParcel1.writeInt(i);
          localParcel1.writeInt(paramInt);
          this.a.transact(6, localParcel1, localParcel2, 0);
          localParcel2.readException();
          return;
        }
        finally
        {
          localParcel2.recycle();
          localParcel1.recycle();
        }
      }
      
      public IBinder asBinder()
      {
        return this.a;
      }
      
      public void b(int paramInt)
      {
        Parcel localParcel1 = Parcel.obtain();
        Parcel localParcel2 = Parcel.obtain();
        try
        {
          localParcel1.writeInterfaceToken("com.google.android.gms.cast.framework.ICastSession");
          localParcel1.writeInt(paramInt);
          this.a.transact(5, localParcel1, localParcel2, 0);
          localParcel2.readException();
          return;
        }
        finally
        {
          localParcel2.recycle();
          localParcel1.recycle();
        }
      }
    }
  }
}


/* Location:              /Users/andi/Downloads/dex2jar-2.0/classes-dex2jar.jar!/com/google/android/gms/cast/framework/u.class
 * Java compiler version: 6 (50.0)
 * JD-Core Version:       0.7.1
 */