package com.google.android.gms.ads.internal.client;

import android.os.Binder;
import android.os.IBinder;
import android.os.IInterface;
import android.os.Parcel;
import com.google.android.gms.ads.internal.formats.NativeAdOptionsParcel;
import com.google.android.gms.ads.internal.formats.k;
import com.google.android.gms.internal.vf;
import com.google.android.gms.internal.vf.a;
import com.google.android.gms.internal.vg;
import com.google.android.gms.internal.vg.a;
import com.google.android.gms.internal.vh;
import com.google.android.gms.internal.vh.a;
import com.google.android.gms.internal.vi;
import com.google.android.gms.internal.vi.a;

public abstract interface ai
  extends IInterface
{
  public abstract ah a();
  
  public abstract void a(ag paramag);
  
  public abstract void a(ao paramao);
  
  public abstract void a(NativeAdOptionsParcel paramNativeAdOptionsParcel);
  
  public abstract void a(vf paramvf);
  
  public abstract void a(vg paramvg);
  
  public abstract void a(String paramString, vi paramvi, vh paramvh);
  
  public static abstract class a
    extends Binder
    implements ai
  {
    public a()
    {
      attachInterface(this, "com.google.android.gms.ads.internal.client.IAdLoaderBuilder");
    }
    
    public static ai a(IBinder paramIBinder)
    {
      if (paramIBinder == null) {
        return null;
      }
      IInterface localIInterface = paramIBinder.queryLocalInterface("com.google.android.gms.ads.internal.client.IAdLoaderBuilder");
      if ((localIInterface != null) && ((localIInterface instanceof ai))) {
        return (ai)localIInterface;
      }
      return new a(paramIBinder);
    }
    
    public IBinder asBinder()
    {
      return this;
    }
    
    public boolean onTransact(int paramInt1, Parcel paramParcel1, Parcel paramParcel2, int paramInt2)
    {
      ah localah = null;
      Object localObject = null;
      switch (paramInt1)
      {
      default: 
        return super.onTransact(paramInt1, paramParcel1, paramParcel2, paramInt2);
      case 1598968902: 
        paramParcel2.writeString("com.google.android.gms.ads.internal.client.IAdLoaderBuilder");
        return true;
      case 1: 
        paramParcel1.enforceInterface("com.google.android.gms.ads.internal.client.IAdLoaderBuilder");
        localah = a();
        paramParcel2.writeNoException();
        paramParcel1 = (Parcel)localObject;
        if (localah != null) {
          paramParcel1 = localah.asBinder();
        }
        paramParcel2.writeStrongBinder(paramParcel1);
        return true;
      case 2: 
        paramParcel1.enforceInterface("com.google.android.gms.ads.internal.client.IAdLoaderBuilder");
        a(ag.a.a(paramParcel1.readStrongBinder()));
        paramParcel2.writeNoException();
        return true;
      case 3: 
        paramParcel1.enforceInterface("com.google.android.gms.ads.internal.client.IAdLoaderBuilder");
        a(vf.a.a(paramParcel1.readStrongBinder()));
        paramParcel2.writeNoException();
        return true;
      case 4: 
        paramParcel1.enforceInterface("com.google.android.gms.ads.internal.client.IAdLoaderBuilder");
        a(vg.a.a(paramParcel1.readStrongBinder()));
        paramParcel2.writeNoException();
        return true;
      case 5: 
        paramParcel1.enforceInterface("com.google.android.gms.ads.internal.client.IAdLoaderBuilder");
        a(paramParcel1.readString(), vi.a.a(paramParcel1.readStrongBinder()), vh.a.a(paramParcel1.readStrongBinder()));
        paramParcel2.writeNoException();
        return true;
      case 6: 
        paramParcel1.enforceInterface("com.google.android.gms.ads.internal.client.IAdLoaderBuilder");
        localObject = localah;
        if (paramParcel1.readInt() != 0) {
          localObject = (NativeAdOptionsParcel)NativeAdOptionsParcel.CREATOR.createFromParcel(paramParcel1);
        }
        a((NativeAdOptionsParcel)localObject);
        paramParcel2.writeNoException();
        return true;
      }
      paramParcel1.enforceInterface("com.google.android.gms.ads.internal.client.IAdLoaderBuilder");
      a(ao.a.a(paramParcel1.readStrongBinder()));
      paramParcel2.writeNoException();
      return true;
    }
    
    private static class a
      implements ai
    {
      private IBinder a;
      
      a(IBinder paramIBinder)
      {
        this.a = paramIBinder;
      }
      
      public ah a()
      {
        Parcel localParcel1 = Parcel.obtain();
        Parcel localParcel2 = Parcel.obtain();
        try
        {
          localParcel1.writeInterfaceToken("com.google.android.gms.ads.internal.client.IAdLoaderBuilder");
          this.a.transact(1, localParcel1, localParcel2, 0);
          localParcel2.readException();
          ah localah = ah.a.a(localParcel2.readStrongBinder());
          return localah;
        }
        finally
        {
          localParcel2.recycle();
          localParcel1.recycle();
        }
      }
      
      /* Error */
      public void a(ag paramag)
      {
        // Byte code:
        //   0: invokestatic 25	android/os/Parcel:obtain	()Landroid/os/Parcel;
        //   3: astore_2
        //   4: invokestatic 25	android/os/Parcel:obtain	()Landroid/os/Parcel;
        //   7: astore_3
        //   8: aload_2
        //   9: ldc 27
        //   11: invokevirtual 31	android/os/Parcel:writeInterfaceToken	(Ljava/lang/String;)V
        //   14: aload_1
        //   15: ifnull +42 -> 57
        //   18: aload_1
        //   19: invokeinterface 58 1 0
        //   24: astore_1
        //   25: aload_2
        //   26: aload_1
        //   27: invokevirtual 61	android/os/Parcel:writeStrongBinder	(Landroid/os/IBinder;)V
        //   30: aload_0
        //   31: getfield 17	com/google/android/gms/ads/internal/client/ai$a$a:a	Landroid/os/IBinder;
        //   34: iconst_2
        //   35: aload_2
        //   36: aload_3
        //   37: iconst_0
        //   38: invokeinterface 37 5 0
        //   43: pop
        //   44: aload_3
        //   45: invokevirtual 40	android/os/Parcel:readException	()V
        //   48: aload_3
        //   49: invokevirtual 52	android/os/Parcel:recycle	()V
        //   52: aload_2
        //   53: invokevirtual 52	android/os/Parcel:recycle	()V
        //   56: return
        //   57: aconst_null
        //   58: astore_1
        //   59: goto -34 -> 25
        //   62: astore_1
        //   63: aload_3
        //   64: invokevirtual 52	android/os/Parcel:recycle	()V
        //   67: aload_2
        //   68: invokevirtual 52	android/os/Parcel:recycle	()V
        //   71: aload_1
        //   72: athrow
        // Local variable table:
        //   start	length	slot	name	signature
        //   0	73	0	this	a
        //   0	73	1	paramag	ag
        //   3	65	2	localParcel1	Parcel
        //   7	57	3	localParcel2	Parcel
        // Exception table:
        //   from	to	target	type
        //   8	14	62	finally
        //   18	25	62	finally
        //   25	48	62	finally
      }
      
      /* Error */
      public void a(ao paramao)
      {
        // Byte code:
        //   0: invokestatic 25	android/os/Parcel:obtain	()Landroid/os/Parcel;
        //   3: astore_2
        //   4: invokestatic 25	android/os/Parcel:obtain	()Landroid/os/Parcel;
        //   7: astore_3
        //   8: aload_2
        //   9: ldc 27
        //   11: invokevirtual 31	android/os/Parcel:writeInterfaceToken	(Ljava/lang/String;)V
        //   14: aload_1
        //   15: ifnull +43 -> 58
        //   18: aload_1
        //   19: invokeinterface 65 1 0
        //   24: astore_1
        //   25: aload_2
        //   26: aload_1
        //   27: invokevirtual 61	android/os/Parcel:writeStrongBinder	(Landroid/os/IBinder;)V
        //   30: aload_0
        //   31: getfield 17	com/google/android/gms/ads/internal/client/ai$a$a:a	Landroid/os/IBinder;
        //   34: bipush 7
        //   36: aload_2
        //   37: aload_3
        //   38: iconst_0
        //   39: invokeinterface 37 5 0
        //   44: pop
        //   45: aload_3
        //   46: invokevirtual 40	android/os/Parcel:readException	()V
        //   49: aload_3
        //   50: invokevirtual 52	android/os/Parcel:recycle	()V
        //   53: aload_2
        //   54: invokevirtual 52	android/os/Parcel:recycle	()V
        //   57: return
        //   58: aconst_null
        //   59: astore_1
        //   60: goto -35 -> 25
        //   63: astore_1
        //   64: aload_3
        //   65: invokevirtual 52	android/os/Parcel:recycle	()V
        //   68: aload_2
        //   69: invokevirtual 52	android/os/Parcel:recycle	()V
        //   72: aload_1
        //   73: athrow
        // Local variable table:
        //   start	length	slot	name	signature
        //   0	74	0	this	a
        //   0	74	1	paramao	ao
        //   3	66	2	localParcel1	Parcel
        //   7	58	3	localParcel2	Parcel
        // Exception table:
        //   from	to	target	type
        //   8	14	63	finally
        //   18	25	63	finally
        //   25	49	63	finally
      }
      
      /* Error */
      public void a(NativeAdOptionsParcel paramNativeAdOptionsParcel)
      {
        // Byte code:
        //   0: invokestatic 25	android/os/Parcel:obtain	()Landroid/os/Parcel;
        //   3: astore_2
        //   4: invokestatic 25	android/os/Parcel:obtain	()Landroid/os/Parcel;
        //   7: astore_3
        //   8: aload_2
        //   9: ldc 27
        //   11: invokevirtual 31	android/os/Parcel:writeInterfaceToken	(Ljava/lang/String;)V
        //   14: aload_1
        //   15: ifnull +42 -> 57
        //   18: aload_2
        //   19: iconst_1
        //   20: invokevirtual 70	android/os/Parcel:writeInt	(I)V
        //   23: aload_1
        //   24: aload_2
        //   25: iconst_0
        //   26: invokevirtual 76	com/google/android/gms/ads/internal/formats/NativeAdOptionsParcel:writeToParcel	(Landroid/os/Parcel;I)V
        //   29: aload_0
        //   30: getfield 17	com/google/android/gms/ads/internal/client/ai$a$a:a	Landroid/os/IBinder;
        //   33: bipush 6
        //   35: aload_2
        //   36: aload_3
        //   37: iconst_0
        //   38: invokeinterface 37 5 0
        //   43: pop
        //   44: aload_3
        //   45: invokevirtual 40	android/os/Parcel:readException	()V
        //   48: aload_3
        //   49: invokevirtual 52	android/os/Parcel:recycle	()V
        //   52: aload_2
        //   53: invokevirtual 52	android/os/Parcel:recycle	()V
        //   56: return
        //   57: aload_2
        //   58: iconst_0
        //   59: invokevirtual 70	android/os/Parcel:writeInt	(I)V
        //   62: goto -33 -> 29
        //   65: astore_1
        //   66: aload_3
        //   67: invokevirtual 52	android/os/Parcel:recycle	()V
        //   70: aload_2
        //   71: invokevirtual 52	android/os/Parcel:recycle	()V
        //   74: aload_1
        //   75: athrow
        // Local variable table:
        //   start	length	slot	name	signature
        //   0	76	0	this	a
        //   0	76	1	paramNativeAdOptionsParcel	NativeAdOptionsParcel
        //   3	68	2	localParcel1	Parcel
        //   7	60	3	localParcel2	Parcel
        // Exception table:
        //   from	to	target	type
        //   8	14	65	finally
        //   18	29	65	finally
        //   29	48	65	finally
        //   57	62	65	finally
      }
      
      /* Error */
      public void a(vf paramvf)
      {
        // Byte code:
        //   0: invokestatic 25	android/os/Parcel:obtain	()Landroid/os/Parcel;
        //   3: astore_2
        //   4: invokestatic 25	android/os/Parcel:obtain	()Landroid/os/Parcel;
        //   7: astore_3
        //   8: aload_2
        //   9: ldc 27
        //   11: invokevirtual 31	android/os/Parcel:writeInterfaceToken	(Ljava/lang/String;)V
        //   14: aload_1
        //   15: ifnull +42 -> 57
        //   18: aload_1
        //   19: invokeinterface 80 1 0
        //   24: astore_1
        //   25: aload_2
        //   26: aload_1
        //   27: invokevirtual 61	android/os/Parcel:writeStrongBinder	(Landroid/os/IBinder;)V
        //   30: aload_0
        //   31: getfield 17	com/google/android/gms/ads/internal/client/ai$a$a:a	Landroid/os/IBinder;
        //   34: iconst_3
        //   35: aload_2
        //   36: aload_3
        //   37: iconst_0
        //   38: invokeinterface 37 5 0
        //   43: pop
        //   44: aload_3
        //   45: invokevirtual 40	android/os/Parcel:readException	()V
        //   48: aload_3
        //   49: invokevirtual 52	android/os/Parcel:recycle	()V
        //   52: aload_2
        //   53: invokevirtual 52	android/os/Parcel:recycle	()V
        //   56: return
        //   57: aconst_null
        //   58: astore_1
        //   59: goto -34 -> 25
        //   62: astore_1
        //   63: aload_3
        //   64: invokevirtual 52	android/os/Parcel:recycle	()V
        //   67: aload_2
        //   68: invokevirtual 52	android/os/Parcel:recycle	()V
        //   71: aload_1
        //   72: athrow
        // Local variable table:
        //   start	length	slot	name	signature
        //   0	73	0	this	a
        //   0	73	1	paramvf	vf
        //   3	65	2	localParcel1	Parcel
        //   7	57	3	localParcel2	Parcel
        // Exception table:
        //   from	to	target	type
        //   8	14	62	finally
        //   18	25	62	finally
        //   25	48	62	finally
      }
      
      /* Error */
      public void a(vg paramvg)
      {
        // Byte code:
        //   0: invokestatic 25	android/os/Parcel:obtain	()Landroid/os/Parcel;
        //   3: astore_2
        //   4: invokestatic 25	android/os/Parcel:obtain	()Landroid/os/Parcel;
        //   7: astore_3
        //   8: aload_2
        //   9: ldc 27
        //   11: invokevirtual 31	android/os/Parcel:writeInterfaceToken	(Ljava/lang/String;)V
        //   14: aload_1
        //   15: ifnull +42 -> 57
        //   18: aload_1
        //   19: invokeinterface 84 1 0
        //   24: astore_1
        //   25: aload_2
        //   26: aload_1
        //   27: invokevirtual 61	android/os/Parcel:writeStrongBinder	(Landroid/os/IBinder;)V
        //   30: aload_0
        //   31: getfield 17	com/google/android/gms/ads/internal/client/ai$a$a:a	Landroid/os/IBinder;
        //   34: iconst_4
        //   35: aload_2
        //   36: aload_3
        //   37: iconst_0
        //   38: invokeinterface 37 5 0
        //   43: pop
        //   44: aload_3
        //   45: invokevirtual 40	android/os/Parcel:readException	()V
        //   48: aload_3
        //   49: invokevirtual 52	android/os/Parcel:recycle	()V
        //   52: aload_2
        //   53: invokevirtual 52	android/os/Parcel:recycle	()V
        //   56: return
        //   57: aconst_null
        //   58: astore_1
        //   59: goto -34 -> 25
        //   62: astore_1
        //   63: aload_3
        //   64: invokevirtual 52	android/os/Parcel:recycle	()V
        //   67: aload_2
        //   68: invokevirtual 52	android/os/Parcel:recycle	()V
        //   71: aload_1
        //   72: athrow
        // Local variable table:
        //   start	length	slot	name	signature
        //   0	73	0	this	a
        //   0	73	1	paramvg	vg
        //   3	65	2	localParcel1	Parcel
        //   7	57	3	localParcel2	Parcel
        // Exception table:
        //   from	to	target	type
        //   8	14	62	finally
        //   18	25	62	finally
        //   25	48	62	finally
      }
      
      /* Error */
      public void a(String paramString, vi paramvi, vh paramvh)
      {
        // Byte code:
        //   0: aconst_null
        //   1: astore 4
        //   3: invokestatic 25	android/os/Parcel:obtain	()Landroid/os/Parcel;
        //   6: astore 5
        //   8: invokestatic 25	android/os/Parcel:obtain	()Landroid/os/Parcel;
        //   11: astore 6
        //   13: aload 5
        //   15: ldc 27
        //   17: invokevirtual 31	android/os/Parcel:writeInterfaceToken	(Ljava/lang/String;)V
        //   20: aload 5
        //   22: aload_1
        //   23: invokevirtual 88	android/os/Parcel:writeString	(Ljava/lang/String;)V
        //   26: aload_2
        //   27: ifnull +68 -> 95
        //   30: aload_2
        //   31: invokeinterface 91 1 0
        //   36: astore_1
        //   37: aload 5
        //   39: aload_1
        //   40: invokevirtual 61	android/os/Parcel:writeStrongBinder	(Landroid/os/IBinder;)V
        //   43: aload 4
        //   45: astore_1
        //   46: aload_3
        //   47: ifnull +10 -> 57
        //   50: aload_3
        //   51: invokeinterface 94 1 0
        //   56: astore_1
        //   57: aload 5
        //   59: aload_1
        //   60: invokevirtual 61	android/os/Parcel:writeStrongBinder	(Landroid/os/IBinder;)V
        //   63: aload_0
        //   64: getfield 17	com/google/android/gms/ads/internal/client/ai$a$a:a	Landroid/os/IBinder;
        //   67: iconst_5
        //   68: aload 5
        //   70: aload 6
        //   72: iconst_0
        //   73: invokeinterface 37 5 0
        //   78: pop
        //   79: aload 6
        //   81: invokevirtual 40	android/os/Parcel:readException	()V
        //   84: aload 6
        //   86: invokevirtual 52	android/os/Parcel:recycle	()V
        //   89: aload 5
        //   91: invokevirtual 52	android/os/Parcel:recycle	()V
        //   94: return
        //   95: aconst_null
        //   96: astore_1
        //   97: goto -60 -> 37
        //   100: astore_1
        //   101: aload 6
        //   103: invokevirtual 52	android/os/Parcel:recycle	()V
        //   106: aload 5
        //   108: invokevirtual 52	android/os/Parcel:recycle	()V
        //   111: aload_1
        //   112: athrow
        // Local variable table:
        //   start	length	slot	name	signature
        //   0	113	0	this	a
        //   0	113	1	paramString	String
        //   0	113	2	paramvi	vi
        //   0	113	3	paramvh	vh
        //   1	43	4	localObject	Object
        //   6	101	5	localParcel1	Parcel
        //   11	91	6	localParcel2	Parcel
        // Exception table:
        //   from	to	target	type
        //   13	26	100	finally
        //   30	37	100	finally
        //   37	43	100	finally
        //   50	57	100	finally
        //   57	84	100	finally
      }
      
      public IBinder asBinder()
      {
        return this.a;
      }
    }
  }
}


/* Location:              /Users/andi/Downloads/dex2jar-2.0/classes-dex2jar.jar!/com/google/android/gms/ads/internal/client/ai.class
 * Java compiler version: 6 (50.0)
 * JD-Core Version:       0.7.1
 */