package com.google.android.gms.auth.api.credentials.internal;

import android.os.Binder;
import android.os.IBinder;
import android.os.IInterface;
import android.os.Parcel;
import android.os.Parcelable.Creator;
import com.google.android.gms.auth.api.credentials.Credential;
import com.google.android.gms.common.api.Status;

public abstract interface j
  extends IInterface
{
  public abstract void a(Status paramStatus);
  
  public abstract void a(Status paramStatus, Credential paramCredential);
  
  public abstract void a(Status paramStatus, String paramString);
  
  public static abstract class a
    extends Binder
    implements j
  {
    public a()
    {
      attachInterface(this, "com.google.android.gms.auth.api.credentials.internal.ICredentialsCallbacks");
    }
    
    public static j a(IBinder paramIBinder)
    {
      if (paramIBinder == null) {
        return null;
      }
      IInterface localIInterface = paramIBinder.queryLocalInterface("com.google.android.gms.auth.api.credentials.internal.ICredentialsCallbacks");
      if ((localIInterface != null) && ((localIInterface instanceof j))) {
        return (j)localIInterface;
      }
      return new a(paramIBinder);
    }
    
    public IBinder asBinder()
    {
      return this;
    }
    
    public boolean onTransact(int paramInt1, Parcel paramParcel1, Parcel paramParcel2, int paramInt2)
    {
      switch (paramInt1)
      {
      default: 
        return super.onTransact(paramInt1, paramParcel1, paramParcel2, paramInt2);
      case 1598968902: 
        paramParcel2.writeString("com.google.android.gms.auth.api.credentials.internal.ICredentialsCallbacks");
        return true;
      case 1: 
        paramParcel1.enforceInterface("com.google.android.gms.auth.api.credentials.internal.ICredentialsCallbacks");
        if (paramParcel1.readInt() != 0)
        {
          localStatus = (Status)Status.CREATOR.createFromParcel(paramParcel1);
          if (paramParcel1.readInt() == 0) {
            break label128;
          }
        }
        for (paramParcel1 = (Credential)Credential.CREATOR.createFromParcel(paramParcel1);; paramParcel1 = null)
        {
          a(localStatus, paramParcel1);
          paramParcel2.writeNoException();
          return true;
          localStatus = null;
          break;
        }
      case 2: 
        label128:
        paramParcel1.enforceInterface("com.google.android.gms.auth.api.credentials.internal.ICredentialsCallbacks");
        if (paramParcel1.readInt() != 0) {}
        for (paramParcel1 = (Status)Status.CREATOR.createFromParcel(paramParcel1);; paramParcel1 = null)
        {
          a(paramParcel1);
          paramParcel2.writeNoException();
          return true;
        }
      }
      paramParcel1.enforceInterface("com.google.android.gms.auth.api.credentials.internal.ICredentialsCallbacks");
      if (paramParcel1.readInt() != 0) {}
      for (Status localStatus = (Status)Status.CREATOR.createFromParcel(paramParcel1);; localStatus = null)
      {
        a(localStatus, paramParcel1.readString());
        paramParcel2.writeNoException();
        return true;
      }
    }
    
    private static class a
      implements j
    {
      private IBinder a;
      
      a(IBinder paramIBinder)
      {
        this.a = paramIBinder;
      }
      
      /* Error */
      public void a(Status paramStatus)
      {
        // Byte code:
        //   0: invokestatic 25	android/os/Parcel:obtain	()Landroid/os/Parcel;
        //   3: astore_2
        //   4: invokestatic 25	android/os/Parcel:obtain	()Landroid/os/Parcel;
        //   7: astore_3
        //   8: aload_2
        //   9: ldc 27
        //   11: invokevirtual 31	android/os/Parcel:writeInterfaceToken	(Ljava/lang/String;)V
        //   14: aload_1
        //   15: ifnull +41 -> 56
        //   18: aload_2
        //   19: iconst_1
        //   20: invokevirtual 35	android/os/Parcel:writeInt	(I)V
        //   23: aload_1
        //   24: aload_2
        //   25: iconst_0
        //   26: invokevirtual 41	com/google/android/gms/common/api/Status:writeToParcel	(Landroid/os/Parcel;I)V
        //   29: aload_0
        //   30: getfield 17	com/google/android/gms/auth/api/credentials/internal/j$a$a:a	Landroid/os/IBinder;
        //   33: iconst_2
        //   34: aload_2
        //   35: aload_3
        //   36: iconst_0
        //   37: invokeinterface 47 5 0
        //   42: pop
        //   43: aload_3
        //   44: invokevirtual 50	android/os/Parcel:readException	()V
        //   47: aload_3
        //   48: invokevirtual 53	android/os/Parcel:recycle	()V
        //   51: aload_2
        //   52: invokevirtual 53	android/os/Parcel:recycle	()V
        //   55: return
        //   56: aload_2
        //   57: iconst_0
        //   58: invokevirtual 35	android/os/Parcel:writeInt	(I)V
        //   61: goto -32 -> 29
        //   64: astore_1
        //   65: aload_3
        //   66: invokevirtual 53	android/os/Parcel:recycle	()V
        //   69: aload_2
        //   70: invokevirtual 53	android/os/Parcel:recycle	()V
        //   73: aload_1
        //   74: athrow
        // Local variable table:
        //   start	length	slot	name	signature
        //   0	75	0	this	a
        //   0	75	1	paramStatus	Status
        //   3	67	2	localParcel1	Parcel
        //   7	59	3	localParcel2	Parcel
        // Exception table:
        //   from	to	target	type
        //   8	14	64	finally
        //   18	29	64	finally
        //   29	47	64	finally
        //   56	61	64	finally
      }
      
      public void a(Status paramStatus, Credential paramCredential)
      {
        Parcel localParcel1 = Parcel.obtain();
        Parcel localParcel2 = Parcel.obtain();
        for (;;)
        {
          try
          {
            localParcel1.writeInterfaceToken("com.google.android.gms.auth.api.credentials.internal.ICredentialsCallbacks");
            if (paramStatus != null)
            {
              localParcel1.writeInt(1);
              paramStatus.writeToParcel(localParcel1, 0);
              if (paramCredential != null)
              {
                localParcel1.writeInt(1);
                paramCredential.writeToParcel(localParcel1, 0);
                this.a.transact(1, localParcel1, localParcel2, 0);
                localParcel2.readException();
              }
            }
            else
            {
              localParcel1.writeInt(0);
              continue;
            }
            localParcel1.writeInt(0);
          }
          finally
          {
            localParcel2.recycle();
            localParcel1.recycle();
          }
        }
      }
      
      /* Error */
      public void a(Status paramStatus, String paramString)
      {
        // Byte code:
        //   0: invokestatic 25	android/os/Parcel:obtain	()Landroid/os/Parcel;
        //   3: astore_3
        //   4: invokestatic 25	android/os/Parcel:obtain	()Landroid/os/Parcel;
        //   7: astore 4
        //   9: aload_3
        //   10: ldc 27
        //   12: invokevirtual 31	android/os/Parcel:writeInterfaceToken	(Ljava/lang/String;)V
        //   15: aload_1
        //   16: ifnull +49 -> 65
        //   19: aload_3
        //   20: iconst_1
        //   21: invokevirtual 35	android/os/Parcel:writeInt	(I)V
        //   24: aload_1
        //   25: aload_3
        //   26: iconst_0
        //   27: invokevirtual 41	com/google/android/gms/common/api/Status:writeToParcel	(Landroid/os/Parcel;I)V
        //   30: aload_3
        //   31: aload_2
        //   32: invokevirtual 61	android/os/Parcel:writeString	(Ljava/lang/String;)V
        //   35: aload_0
        //   36: getfield 17	com/google/android/gms/auth/api/credentials/internal/j$a$a:a	Landroid/os/IBinder;
        //   39: iconst_3
        //   40: aload_3
        //   41: aload 4
        //   43: iconst_0
        //   44: invokeinterface 47 5 0
        //   49: pop
        //   50: aload 4
        //   52: invokevirtual 50	android/os/Parcel:readException	()V
        //   55: aload 4
        //   57: invokevirtual 53	android/os/Parcel:recycle	()V
        //   60: aload_3
        //   61: invokevirtual 53	android/os/Parcel:recycle	()V
        //   64: return
        //   65: aload_3
        //   66: iconst_0
        //   67: invokevirtual 35	android/os/Parcel:writeInt	(I)V
        //   70: goto -40 -> 30
        //   73: astore_1
        //   74: aload 4
        //   76: invokevirtual 53	android/os/Parcel:recycle	()V
        //   79: aload_3
        //   80: invokevirtual 53	android/os/Parcel:recycle	()V
        //   83: aload_1
        //   84: athrow
        // Local variable table:
        //   start	length	slot	name	signature
        //   0	85	0	this	a
        //   0	85	1	paramStatus	Status
        //   0	85	2	paramString	String
        //   3	77	3	localParcel1	Parcel
        //   7	68	4	localParcel2	Parcel
        // Exception table:
        //   from	to	target	type
        //   9	15	73	finally
        //   19	30	73	finally
        //   30	55	73	finally
        //   65	70	73	finally
      }
      
      public IBinder asBinder()
      {
        return this.a;
      }
    }
  }
}


/* Location:              /Users/andi/Downloads/dex2jar-2.0/classes-dex2jar.jar!/com/google/android/gms/auth/api/credentials/internal/j.class
 * Java compiler version: 6 (50.0)
 * JD-Core Version:       0.7.1
 */